Workbook

Sheet Read Me First
A1: How To Use This Workbook
A3: WHAT CONVOY IS:
A4: Convoy is a Mad Max-meets-Silk Road trading and piracy game. In the eventual human-facing version, players
A5: mine and refine raw materials, form convoys to move goods along a single dangerous road connecting Refinery
A6: Row to Town, and can either protect that trade or prey on it. Wealth, politics, crime, and reputation are
A7: all governed by a player-driven economy rather than fixed NPC systems.
A9: WHAT THIS BUILD IS:
A10: This is NOT that game. It's an agent-only economic sandbox with no human players and no 3D rendering.
A11: 75 AI agents (15 each across 5 different models, accessed through OpenRouter) live in this Bronze Age
A12: economy for 120 real hours, no time compression, making every decision themselves — mining, trading,
A13: starting businesses, joining or robbing convoys, voting on policy, fighting. Every agent's single goal is
A14: to maximize their own Net Worth by the end of the run — there is no other win condition.
... A63: itself determines accuracy over time.

Sheet Master Overview
A1: Convoy — Master Overview
A2: One-glance summary of every tab. Edit source tabs to change values — everything here is a live formula.
A4: CURRENCY & STARTING POINT
A5: Currency Name | B5: =Assumptions!C5 -> Denari | D5: Starting Denari | E5: =Assumptions!C6 -> 100
A7: RESOURCES (15 — raw + refined, Bronze & Iron)
A8: Resource | B8: Rarity | C8: Base Price | D8: NPC Buy | E8: NPC Sell | F8: Source
A9: =Resources!A5 -> Water | B9: =Resources!B5 -> Common | C9: =Resources!D5 -> 1 | D9: =Resources!E5 -> 0.4 | E9: =Resources!F5 -> 1.6 | F9: =Resources!C5 -> Farms/Wells
A10: =Resources!A6 -> Grain | B10: =Resources!B6 -> Common | C10: =Resources!D6 -> 2 | D10: =Resources!E6 -> 0.8 | E10: =Resources!F6 -> 3.2 | F10: =Resources!C6 -> Farms
A11: =Resources!A7 -> Wood | B11: =Resources!B7 -> Common | C11: =Resources!D7 -> 2 | D11: =Resources!E7 -> 0.8 | E11: =Resources!F7 -> 3.2 | F11: =Resources!C7 -> Mines/Logging
A12: =Resources!A8 -> Stone | B12: =Resources!B8 -> Common | C12: =Resources!D8 -> 3 | D12: =Resources!E8 -> 1.2 | E12: =Resources!F8 -> 4.8 | F12: =Resources!C8 -> Mines
A13: =Resources!A9 -> Clay | B13: =Resources!B9 -> Common | C13: =Resources!D9 -> 2 | D13: =Resources!E9 -> 0.8 | E13: =Resources!F9 -> 3.2 | F13: =Resources!C9 -> Mines
A14: =Resources!A10 -> Hide | B14: =Resources!B10 -> Common | C14: =Resources!D10 -> 4 | D14: =Resources!E10 -> 1.6 | E14: =Resources!F10 -> 6.4 | F14: =Resources!C10 -> Farms (livestock)
A15: =Resources!A11 -> Copper Ore | B15: =Resources!B11 -> Uncommon | C15: =Resources!D11 -> 6 | D15: =Resources!E11 -> 2.4 | E15: =Resources!F11 -> 9.6 | F15: =Resources!C11 -> Mines
A16: =Resources!A12 -> Tin Ore | B16: =Resources!B12 -> Uncommon | C16: =Resources!D12 -> 8 | D16: =Resources!E12 -> 3.2 | E16: =Resources!F12 -> 12.8 | F16: =Resources!C12 -> Mines
A17: =Resources!A13 -> Bronze (refined) | B17: =Resources!B13 -> Uncommon | C17: =Resources!D13 -> 18 | D17: =Resources!E13 -> 7.2 | E17: =Resources!F13 -> 28.8 | F17: =Resources!C13 -> Refinery (Copper + Tin + Charcoal)
A18: =Resources!A14 -> Charcoal (refined) | B18: =Resources!B14 -> Uncommon | C18: =Resources!D14 -> 4 | D18: =Resources!E14 -> 1.6 | E18: =Resources!F14 -> 6.4 | F18: =Resources!C14 -> Refinery (Wood)
A19: =Resources!A15 -> Tanned Leather (refined) | B19: =Resources!B15 -> Uncommon | C19: =Resources!D15 -> 7 | D19: =Resources!E15 -> 2.8 | E19: =Resources!F15 -> 11.2 | F19: =Resources!C15 -> Refinery (Hide + Water)
A20: =Resources!A16 -> Iron Ore | B20: =Resources!B16 -> Uncommon | C20: =Resources!D16 -> 12 | D20: =Resources!E16 -> 4.8 | E20: =Resources!F16 -> 19.2 | F20: =Resources!C16 -> Mines
... A23: =Resources!A19 -> Iron (refined) | B23: =Resources!B19 -> Rare | C23: =Resources!D19 -> 22 | D23: =Resources!E19 -> 8.8 | E23: =Resources!F19 -> 35.2 | F23: =Resources!C19 -> Refinery (Iron Ore + Charcoal)
A25: VEHICLES (6)
A26: Vehicle | B26: Rarity | C26: Speed | D26: Cargo (units) | E26: Base Price | F26: NPC Sell Price
A27: =Vehicles!A5 -> On Foot (backpack) | B27: =Vehicles!B5 -> Common | C27: =Vehicles!C5 -> Slowest | D27: =Vehicles!D5 -> 5 | E27: =Vehicles!F5 -> 0 | F27: =Vehicles!G5 -> 0
A28: =Vehicles!A6 -> Camel | B28: =Vehicles!B6 -> Common | C28: =Vehicles!C6 -> Slow | D28: =Vehicles!D6 -> 20 | E28: =Vehicles!F6 -> 150 | F28: =Vehicles!G6 -> 225
A29: =Vehicles!A7 -> Horse | B29: =Vehicles!B7 -> Common | C29: =Vehicles!C7 -> Medium | D29: =Vehicles!D7 -> 15 | E29: =Vehicles!F7 -> 200 | F29: =Vehicles!G7 -> 300
A30: =Vehicles!A8 -> Donkey Cart | B30: =Vehicles!B8 -> Uncommon | C30: =Vehicles!C8 -> Slow | D30: =Vehicles!D8 -> 100 | E30: =Vehicles!F8 -> 400 | F30: =Vehicles!G8 -> 600
A31: =Vehicles!A9 -> 2-Horse Chariot | B31: =Vehicles!B9 -> Rare | C31: =Vehicles!C9 -> Fast | D31: =Vehicles!D9 -> 80 | E31: =Vehicles!F9 -> 700 | F31: =Vehicles!G9 -> 1050
A32: =Vehicles!A10 -> 4-Horse Chariot | B32: =Vehicles!B10 -> Rare | C32: =Vehicles!C10 -> Fastest | D32: =Vehicles!D10 -> 200 | E32: =Vehicles!F10 -> 1600 | F32: =Vehicles!G10 -> 2400
A34: WEAPONS (10)
A35: Weapon | B35: Rarity | C35: Type | D35: Damage | E35: Base Price | F35: NPC Sell Price
A36: =Weapons!A5 -> Slingshot | B36: =Weapons!B5 -> Common | C36: =Weapons!C5 -> Ranged (starter) | D36: =Weapons!D5 -> 10 | E36: =Weapons!E5 -> 0 | F36: =Weapons!F5 -> 0
A37: =Weapons!A6 -> Sling | B37: =Weapons!B6 -> Common | C37: =Weapons!C6 -> Ranged | D37: =Weapons!D6 -> 14 | E37: =Weapons!E6 -> 50 | F37: =Weapons!F6 -> 85
A38: =Weapons!A7 -> Wooden Spear | B38: =Weapons!B7 -> Common | C38: =Weapons!C7 -> Melee | D38: =Weapons!D7 -> 22 | E38: =Weapons!E7 -> 60 | F38: =Weapons!F7 -> 102
A39: =Weapons!A8 -> Bronze Dagger | B39: =Weapons!B8 -> Uncommon | C39: =Weapons!C8 -> Melee | D39: =Weapons!D8 -> 16 | E39: =Weapons!E8 -> 120 | F39: =Weapons!F8 -> 204
A40: =Weapons!A9 -> Bronze-Tipped Spear | B40: =Weapons!B9 -> Uncommon | C40: =Weapons!C9 -> Melee | D40: =Weapons!D9 -> 28 | E40: =Weapons!E9 -> 220 | F40: =Weapons!F9 -> 374
A41: =Weapons!A10 -> Bronze Sword | B41: =Weapons!B10 -> Uncommon | C41: =Weapons!C10 -> Melee | D41: =Weapons!D10 -> 34 | E41: =Weapons!E10 -> 250 | F41: =Weapons!F10 -> 425
A42: =Weapons!A11 -> Bow | B42: =Weapons!B11 -> Rare | C42: =Weapons!C11 -> Ranged | D42: =Weapons!D11 -> 20 | E42: =Weapons!E11 -> 300 | F42: =Weapons!F11 -> 510
A43: =Weapons!A12 -> Iron Dagger | B43: =Weapons!B12 -> Rare | C43: =Weapons!C12 -> Melee | D43: =Weapons!D12 -> 24 | E43: =Weapons!E12 -> 350 | F43: =Weapons!F12 -> 595
A44: =Weapons!A13 -> Iron-Tipped Spear | B44: =Weapons!B13 -> Rare | C44: =Weapons!C13 -> Melee | D44: =Weapons!D13 -> 36 | E44: =Weapons!E13 -> 550 | F44: =Weapons!F13 -> 935
A45: =Weapons!A14 -> Iron Sword | B45: =Weapons!B14 -> Rare | C45: =Weapons!C14 -> Melee | D45: =Weapons!D14 -> 50 | E45: =Weapons!E14 -> 650 | F45: =Weapons!F14 -> 1105
A47: ARMOR (9)
A48: Armor Piece | B48: Slot | C48: Tier | D48: Reduction | E48: Base Price | F48: NPC Sell Price
A49: =Armor!A5 -> Leather Cap | B49: =Armor!B5 -> Head | C49: =Armor!C5 -> Leather | D49: =Armor!D5 -> -0.05 | E49: =Armor!F5 -> 80 | F49: =Armor!G5 -> 136
A50: =Armor!A6 -> Leather Vest | B50: =Armor!B6 -> Chest | C50: =Armor!C6 -> Leather | D50: =Armor!D6 -> -0.1 | E50: =Armor!F6 -> 150 | F50: =Armor!G6 -> 255
A51: =Armor!A7 -> Leather Leggings | B51: =Armor!B7 -> Legs | C51: =Armor!C7 -> Leather | D51: =Armor!D7 -> -0.05 | E51: =Armor!F7 -> 80 | F51: =Armor!G7 -> 136
A52: =Armor!A8 -> Bronze Helm | B52: =Armor!B8 -> Head | C52: =Armor!C8 -> Bronze | D52: =Armor!D8 -> -0.1 | E52: =Armor!F8 -> 300 | F52: =Armor!G8 -> 510
A53: =Armor!A9 -> Bronze Cuirass | B53: =Armor!B9 -> Chest | C53: =Armor!C9 -> Bronze | D53: =Armor!D9 -> -0.2 | E53: =Armor!F9 -> 550 | F53: =Armor!G9 -> 935
A54: =Armor!A10 -> Bronze Greaves | B54: =Armor!B10 -> Legs | C54: =Armor!C10 -> Bronze | D54: =Armor!D10 -> -0.1 | E54: =Armor!F10 -> 300 | F54: =Armor!G10 -> 510
A55: =Armor!A11 -> Iron Helm | B55: =Armor!B11 -> Head | C55: =Armor!C11 -> Iron | D55: =Armor!D11 -> -0.15 | E55: =Armor!F11 -> 500 | F55: =Armor!G11 -> 850
A56: =Armor!A12 -> Iron Cuirass | B56: =Armor!B12 -> Chest | C56: =Armor!C12 -> Iron | D56: =Armor!D12 -> -0.25 | E56: =Armor!F12 -> 900 | F56: =Armor!G12 -> 1530
A57: =Armor!A13 -> Iron Greaves | B57: =Armor!B13 -> Legs | C57: =Armor!C13 -> Iron | D57: =Armor!D13 -> -0.15 | E57: =Armor!F13 -> 500 | F57: =Armor!G13 -> 850
A59: BUSINESSES (11)
A60: Business | B60: Startup Cost | C60: Employees Required? | D60: Max Employees
A61: =Businesses!A5 -> Mining Operation | B61: =Businesses!B5 -> 350 | C61: =Businesses!D5 -> Required — zero output with no active worker (owner can self-staff) | D61: =Businesses!E5 -> Uncapped
A62: =Businesses!A6 -> Farm | B62: =Businesses!B6 -> 300 | C62: =Businesses!D6 -> Required — zero output with no active worker (owner can self-staff) | D62: =Businesses!E6 -> Uncapped
A63: =Businesses!A7 -> Refinery | B63: =Businesses!B7 -> 900 | C63: =Businesses!D7 -> Required — zero output with no active worker (owner can self-staff) | D63: =Businesses!E7 -> Uncapped
A64: =Businesses!A8 -> General Store | B64: =Businesses!B8 -> 500 | C64: =Businesses!D8 -> Required for extended hours | D64: =Businesses!E8 -> 2
A65: =Businesses!A9 -> Home Improvement Store | B65: =Businesses!B9 -> 500 | C65: =Businesses!D9 -> Required for extended hours | D65: =Businesses!E9 -> 2
A66: =Businesses!A10 -> Mining/Farming Equipment Store | B66: =Businesses!B10 -> 550 | C66: =Businesses!D10 -> Required for extended hours | D66: =Businesses!E10 -> 2
A67: =Businesses!A11 -> Weaponsmith / Armory | B67: =Businesses!B11 -> 700 | C67: =Businesses!D11 -> Required for extended hours | D67: =Businesses!E11 -> 2
A68: =Businesses!A12 -> Vehicle Dealer / Stable | B68: =Businesses!B12 -> 600 | C68: =Businesses!D12 -> Required for extended hours | D68: =Businesses!E12 -> 2
A69: =Businesses!A13 -> Tavern / Inn | B69: =Businesses!B13 -> 400 | C69: =Businesses!D13 -> Required for extended hours | D69: =Businesses!E13 -> 2
A70: =Businesses!A14 -> Private Security Contractor | B70: =Businesses!B14 -> 1000 | C70: =Businesses!D14 -> Guards ARE the employees | D70: =Businesses!E14 -> N/A
A71: =Businesses!A15 -> Insurance Brokerage | B71: =Businesses!B15 -> 1500 | C71: =Businesses!D15 -> None — capital reserve instead | D71: =Businesses!E15 -> 0
A73: WAGES (per hour)
A74: Role | B74: NPC Wage | C74: Smart Player Wage | D74: Minimum Wage Floor
A75: =Wages!A5 -> Laborer | B75: =Wages!B5 -> 45 | C75: =Wages!C5 -> 20 | D75: =Wages!D5 -> 10
A76: =Wages!A6 -> Miner (uncommon ore) | B76: =Wages!B6 -> 65 | C76: =Wages!C6 -> 28.888889 | D76: =Wages!D6 -> 14.444444
A77: =Wages!A7 -> Farmhand | B77: =Wages!B7 -> 50 | C77: =Wages!C7 -> 22.222222 | D77: =Wages!D7 -> 11.111111
A78: =Wages!A8 -> Refinery Worker | B78: =Wages!B8 -> 85 | C78: =Wages!C8 -> 37.777778 | D78: =Wages!D8 -> 18.888889
A79: =Wages!A9 -> Store Clerk | B79: =Wages!B9 -> 40 | C79: =Wages!C9 -> 17.777778 | D79: =Wages!D9 -> 8.8888889
A80: =Wages!A10 -> Blacksmith | B80: =Wages!B10 -> 80 | C80: =Wages!C10 -> 35.555556 | D80: =Wages!D10 -> 17.777778
A81: =Wages!A11 -> Stablehand | B81: =Wages!B11 -> 45 | C81: =Wages!C11 -> 20 | D81: =Wages!D11 -> 10
A82: =Wages!A12 -> Researcher | B82: =Wages!B12 -> 75 | C82: =Wages!C12 -> 33.333333 | D82: =Wages!D12 -> 16.666667
A84: RESEARCH TIERS
A85: Tier | B85: Cumulative RP | C85: Hours (1 Researcher) | D85: Efficiency | E85: Quality | F85: Tag
A86: =Research!A10 -> Tier 1 | B86: =Research!B10 -> 150 | C86: =Research!C10 -> 18.75 | D86: =Research!D10 -> 0.05 | E86: =Research!E10 -> 0.05 | F86: =Research!F10 -> —
A87: =Research!A11 -> Tier 2 | B87: =Research!B11 -> 400 | C87: =Research!C11 -> 50 | D87: =Research!D11 -> 0.1 | E87: =Research!E11 -> 0.1 | F87: =Research!F11 -> —
A88: =Research!A12 -> Tier 3 | B88: =Research!B12 -> 900 | C88: =Research!C12 -> 112.5 | D88: =Research!D12 -> 0.15 | E88: =Research!E12 -> 0.15 | F88: =Research!F12 -> Fine
A89: =Research!A13 -> Tier 4 | B89: =Research!B13 -> 1800 | C89: =Research!C13 -> 225 | D89: =Research!D13 -> 0.2 | E89: =Research!E13 -> 0.2 | F89: =Research!F13 -> Masterwork
A90: =Research!A14 -> Tier 5 | B90: =Research!B14 -> 3500 | C90: =Research!C14 -> 437.5 | D90: =Research!D14 -> 0.25 | E90: =Research!E14 -> 0.25 | F90: =Research!F14 -> Legendary Craftsmanship
A92: Full agent action/tool list (~94 actions across 17 categories) lives on its own Actions tab. Convoy roles/pay formula and Government/Insurance policy catalog & bounty rules live on their own tabs — all three too long to usefully summarize here.

Sheet Assumptions
A1: Convoy — Iron Age Economy Assumptions
A2: Edit yellow cells to rebalance the entire economy. All other sheets pull from here.
A4: Category | B4: Assumption | C4: Value | D4: Notes
A5: Currency | B5: Currency Name | C5: Denari | D5: Bronze Age silver coin
A6: Player Start | B6: Starting Denari | C6: 100
A7: NPC Trading Post | B7: NPC Buy % of Base Price (raw resources) | C7: 0.4 | D7: NPC pays this % of base price when buying from players
A8: NPC General Store | B8: NPC Sell % of Base Price (common goods) | C8: 1.6 | D8: NPC charges this % of base price when selling to players
A9: NPC Refinery | B9: NPC Buy % of Base Price (ore) | C9: 0.4 | D9: Same as Trading Post rate
A10: NPC Refinery | B10: NPC Sell % of Base Price (refined goods) | C10: 1.5
A11: NPC Weaponsmith | B11: NPC Sell % of Base Price (weapons & armor) | C11: 1.7 | D11: Highest markup — biggest entrepreneurship incentive
A12: NPC Stables | B12: NPC Sell % of Base Price (vehicles) | C12: 1.5
A13: NPC Insurance | B13: NPC Premium % of Cargo Value | C13: 0.2 | D13: Player brokers can undercut to ~8-12%
A14: Player Store Floor | B14: Minimum Retail % of Base Price | C14: 0.6 | D14: Players cannot undercut below this — prevents predatory pricing wars
A15: Wages | B15: NPC Employee Wage Multiplier (vs Smart Player Wage) | C15: 2.25 | D15: NPC employees cost this many times the smart player wage
A16: Wages | B16: Minimum Player Wage % of Smart Wage | C16: 0.5 | D16: Soft floor — owners can't pay below this
A17: Production | B17: Employee Speed Bonus (per employee) | C17: 0.4 | D17: +40% output speed per employee, up to 3 employees
A18: Production | B18: Max Employees per Production Business | C18: 3
A19: Business | B19: Bankruptcy Grace Period (hours) | C19: 24 | D19: Time after cash hits zero before business closes
A20: Research | B20: RP Generated per Researcher per Hour | C20: 8 | D20: Stated assumption — no other data to derive this from
A21: Taxes | B21: Default Wage Tax % | C21: 0.05 | D21: Adjustable via Government policy — bounded 0-25%
A22: Taxes | B22: Default Sales Tax % | C22: 0.05 | D22: Adjustable via Government policy — bounded 0-25%
A23: Taxes | B23: Default Property Tax % | C23: 0.05 | D23: Charged every 24 real hours on assessed value. Adjustable via policy — bounded 0-25%

Sheet Resources
A1: Resources — Bronze & Iron
A2: Base Price is the reference value. NPC Buy/Sell prices auto-calculate from Assumptions tab. Base Rate/hr is per single worker (Novice skill, no diminishing returns) — see Businesses tab for how output scales with employee count. See Production Chain tab for how raw resources become refined resources become final goods. Recipe quantities are fixed — Research changes speed and output quality, never these input amounts.
A4: Resource | B4: Rarity | C4: Source | D4: Base Price | E4: NPC Buy Price (Trading Post) | F4: NPC Sell Price (General Store) | G4: Used For | H4: Base Rate/hr (1 worker)
A5: Water | B5: Common | C5: Farms/Wells | D5: 1 | E5: =D5*Assumptions!C7 -> 0.4 | F5: =D5*Assumptions!C8 -> 1.6 | G5: Food/survival, Tanned Leather (refined) | H5: 72
A6: Grain | B6: Common | C6: Farms | D6: 2 | E6: =D6*Assumptions!C7 -> 0.8 | F6: =D6*Assumptions!C8 -> 3.2 | G6: Food/survival, Tavern meals | H6: 72
A7: Wood | B7: Common | C7: Mines/Logging | D7: 2 | E7: =D7*Assumptions!C7 -> 0.8 | F7: =D7*Assumptions!C8 -> 3.2 | G7: Charcoal (refined), weapon handles, cart frames, tools, property upgrades | H7: 72
A8: Stone | B8: Common | C8: Mines | D8: 3 | E8: =D8*Assumptions!C7 -> 1.2 | F8: =D8*Assumptions!C8 -> 4.8 | G8: Property upgrades | H8: 72
A9: Clay | B9: Common | C9: Mines | D9: 2 | E9: =D9*Assumptions!C7 -> 0.8 | F9: =D9*Assumptions!C8 -> 3.2 | G9: Property upgrades | H9: 72
A10: Hide | B10: Common | C10: Farms (livestock) | D10: 4 | E10: =D10*Assumptions!C7 -> 1.6 | F10: =D10*Assumptions!C8 -> 6.4 | G10: Tanned Leather (refined) | H10: 72
A11: Copper Ore | B11: Uncommon | C11: Mines | D11: 6 | E11: =D11*Assumptions!C7 -> 2.4 | F11: =D11*Assumptions!C8 -> 9.6 | G11: Bronze (refined) | H11: 36
A12: Tin Ore | B12: Uncommon | C12: Mines | D12: 8 | E12: =D12*Assumptions!C7 -> 3.2 | F12: =D12*Assumptions!C8 -> 12.8 | G12: Bronze (refined) | H12: 36
A13: Bronze (refined) | B13: Uncommon | C13: Refinery (Copper + Tin + Charcoal) | D13: 18 | E13: =D13*Assumptions!C7 -> 7.2 | F13: =D13*Assumptions!C8 -> 28.8 | G13: Bronze weapons/armor, cart reinforcement, tools | H13: 15
A14: Charcoal (refined) | B14: Uncommon | C14: Refinery (Wood) | D14: 4 | E14: =D14*Assumptions!C7 -> 1.6 | F14: =D14*Assumptions!C8 -> 6.4 | G14: Bronze and Iron smelting fuel | H14: 15
A15: Tanned Leather (refined) | B15: Uncommon | C15: Refinery (Hide + Water) | D15: 7 | E15: =D15*Assumptions!C7 -> 2.8 | F15: =D15*Assumptions!C8 -> 11.2 | G15: Slings, bows, all armor tiers, harnesses, chariot tack | H15: 15
A16: Iron Ore | B16: Uncommon | C16: Mines | D16: 12 | E16: =D16*Assumptions!C7 -> 4.8 | F16: =D16*Assumptions!C8 -> 19.2 | G16: Iron (refined) | H16: 36
A17: Hardwood | B17: Uncommon | C17: Mines/Logging | D17: 8 | E17: =D17*Assumptions!C7 -> 3.2 | F17: =D17*Assumptions!C8 -> 12.8 | G17: Iron Age weapons, chariots, Bow | H17: 36
A18: Wool | B18: Common | C18: Farms | D18: 5 | E18: =D18*Assumptions!C7 -> 2 | F18: =D18*Assumptions!C8 -> 8 | G18: Clothing/cosmetics | H18: 72
A19: Iron (refined) | B19: Rare | C19: Refinery (Iron Ore + Charcoal) | D19: 22 | E19: =D19*Assumptions!C7 -> 8.8 | F19: =D19*Assumptions!C8 -> 35.2 | G19: Iron weapons, Iron armor, 4-Horse Chariot | H19: 15

Sheet Production Chain
A1: Production Chain — Raw → Refined → Final Goods
A2: Three stages: Mine/Farm extracts raw resources, Refinery processes them into refined resources, Store does final assembly and sells to players. Input Cost columns sum base prices from the Resources/Weapons/Vehicles/Armor tabs — edit those to see costs and margins update here automatically. These recipe quantities are fixed regardless of Research investment (see Research tab).
A4: STAGE 1 — RAW (Mined or Farmed)
A5: Resource | B5: Source | C5: Feeds Into
A6: =Resources!A5 -> Water | B6: =Resources!C5 -> Farms/Wells | C6: =Resources!G5 -> Food/survival, Tanned Leather (refined)
A7: =Resources!A6 -> Grain | B7: =Resources!C6 -> Farms | C7: =Resources!G6 -> Food/survival, Tavern meals
A8: =Resources!A7 -> Wood | B8: =Resources!C7 -> Mines/Logging | C8: =Resources!G7 -> Charcoal (refined), weapon handles, cart frames, tools, property upgrades
A9: =Resources!A8 -> Stone | B9: =Resources!C8 -> Mines | C9: =Resources!G8 -> Property upgrades
A10: =Resources!A9 -> Clay | B10: =Resources!C9 -> Mines | C10: =Resources!G9 -> Property upgrades
A11: =Resources!A10 -> Hide | B11: =Resources!C10 -> Farms (livestock) | C11: =Resources!G10 -> Tanned Leather (refined)
A12: =Resources!A11 -> Copper Ore | B12: =Resources!C11 -> Mines | C12: =Resources!G11 -> Bronze (refined)
A13: =Resources!A12 -> Tin Ore | B13: =Resources!C12 -> Mines | C13: =Resources!G12 -> Bronze (refined)
A14: =Resources!A16 -> Iron Ore | B14: =Resources!C16 -> Mines | C14: =Resources!G16 -> Iron (refined)
A15: =Resources!A17 -> Hardwood | B15: =Resources!C17 -> Mines/Logging | C15: =Resources!G17 -> Iron Age weapons, chariots, Bow
A16: =Resources!A18 -> Wool | B16: =Resources!C18 -> Farms | C16: =Resources!G18 -> Clothing/cosmetics
A18: STAGE 2 — REFINED (at Refinery)
A19: Refined Good | B19: Inputs Required | C19: Input Cost (sum of base prices) | D19: Base Price (this good) | E19: Margin | F19: Used For
A20: Charcoal | B20: Wood | C20: =Resources!D7 -> 2 | D20: =Resources!D14 -> 4 | E20: =D20-C20 -> 2 | F20: Bronze and Iron smelting fuel
A21: Tanned Leather | B21: Hide + Water | C21: =Resources!D10+Resources!D5 -> 5 | D21: =Resources!D15 -> 7 | E21: =D21-C21 -> 2 | F21: Slings, bows, all armor tiers, harnesses, chariot tack
A22: Bronze | B22: Copper Ore + Tin Ore + Charcoal | C22: =Resources!D11+Resources!D12+Resources!D14 -> 18 | D22: =Resources!D13 -> 18 | E22: =D22-C22 -> 0 | F22: Bronze weapons/armor, cart reinforcement, tools
A23: Iron | B23: Iron Ore + Charcoal | C23: =Resources!D16+Resources!D14 -> 16 | D23: =Resources!D19 -> 22 | E23: =D23-C23 -> 6 | F23: Iron weapons/armor, 4-Horse Chariot
A25: STAGE 3 — FINAL GOODS (assembled + sold at Stores)
A26: Final Good | B26: Assembled At | C26: Inputs Required | D26: Input Cost (sum of base prices) | E26: Sell Price (base, this good) | F26: Margin
A27: Sling | B27: Weaponsmith | C27: Tanned Leather + Wood | D27: =Resources!D15+Resources!D7 -> 9 | E27: =Weapons!E6 -> 50 | F27: =E27-D27 -> 41
A28: Wooden Spear | B28: Weaponsmith | C28: Wood | D28: =Resources!D7 -> 2 | E28: =Weapons!E7 -> 60 | F28: =E28-D28 -> 58
A29: Bronze Dagger | B29: Weaponsmith | C29: Bronze + Wood | D29: =Resources!D13+Resources!D7 -> 20 | E29: =Weapons!E8 -> 120 | F29: =E29-D29 -> 100
A30: Bronze-Tipped Spear | B30: Weaponsmith | C30: Bronze + Wood | D30: =Resources!D13+Resources!D7 -> 20 | E30: =Weapons!E9 -> 220 | F30: =E30-D30 -> 200
A31: Bronze Sword | B31: Weaponsmith | C31: Bronze + Wood | D31: =Resources!D13+Resources!D7 -> 20 | E31: =Weapons!E10 -> 250 | F31: =E31-D31 -> 230
A32: Bow | B32: Weaponsmith | C32: Hardwood + Tanned Leather | D32: =Resources!D17+Resources!D15 -> 15 | E32: =Weapons!E11 -> 300 | F32: =E32-D32 -> 285
A33: Iron Dagger | B33: Weaponsmith | C33: Iron + Hardwood | D33: =Resources!D19+Resources!D17 -> 30 | E33: =Weapons!E12 -> 350 | F33: =E33-D33 -> 320
A34: Iron-Tipped Spear | B34: Weaponsmith | C34: Iron + Hardwood | D34: =Resources!D19+Resources!D17 -> 30 | E34: =Weapons!E13 -> 550 | F34: =E34-D34 -> 520
A35: Iron Sword | B35: Weaponsmith | C35: Iron + Hardwood | D35: =Resources!D19+Resources!D17 -> 30 | E35: =Weapons!E14 -> 650 | F35: =E35-D35 -> 620
A36: Leather Cap/Vest/Leggings (each) | B36: Weaponsmith | C36: Tanned Leather | D36: =Resources!D15 -> 7 | E36: =Armor!F5 -> 80 | F36: =E36-D36 -> 73
A37: Bronze Helm/Cuirass/Greaves (each) | B37: Weaponsmith | C37: Bronze + Tanned Leather | D37: =Resources!D13+Resources!D15 -> 25 | E37: =Armor!F8 -> 300 | F37: =E37-D37 -> 275
A38: Iron Helm/Cuirass/Greaves (each) | B38: Weaponsmith | C38: Iron + Tanned Leather | D38: =Resources!D19+Resources!D15 -> 29 | E38: =Armor!F11 -> 500 | F38: =E38-D38 -> 471
A39: Donkey Cart | B39: Vehicle Dealer / Stable | C39: Wood + Bronze + Tanned Leather | D39: =Resources!D7+Resources!D13+Resources!D15 -> 27 | E39: =Vehicles!F8 -> 400 | F39: =E39-D39 -> 373
A40: 2-Horse Chariot | B40: Vehicle Dealer / Stable | C40: Hardwood + Tanned Leather | D40: =Resources!D17+Resources!D15 -> 15 | E40: =Vehicles!F9 -> 700 | F40: =E40-D40 -> 685
A41: 4-Horse Chariot | B41: Vehicle Dealer / Stable | C41: Iron + Hardwood + Tanned Leather | D41: =Resources!D19+Resources!D17+Resources!D15 -> 37 | E41: =Vehicles!F10 -> 1600 | F41: =E41-D41 -> 1563
A42: Camel | B42: Vehicle Dealer / Stable | C42: 15 Water + 10 Grain + 1 Tanned Leather (feed + saddle) | D42: =Resources!D5*15+Resources!D6*10+Resources!D15*1 -> 42 | E42: =Vehicles!F6 -> 150 | F42: =E42-D42 -> 108
A43: Horse | B43: Vehicle Dealer / Stable | C43: 20 Water + 15 Grain + 1 Tanned Leather (feed + saddle) | D43: =Resources!D5*20+Resources!D6*15+Resources!D15*1 -> 57 | E43: =Vehicles!F7 -> 200 | F43: =E43-D43 -> 143
A44: Upgraded Tools | B44: Mining/Farming Equipment Store | C44: Wood + Bronze | D44: =Resources!D7+Resources!D13 -> 20 | E44: 130 | F44: =E44-D44 -> 110
A45: Property Upgrades | B45: Home Improvement Store | C45: Stone + Clay + Wood | D45: =Resources!D8+Resources!D9+Resources!D7 -> 7 | E45: 50 | F45: =E45-D45 -> 43
A46: Food (resale) | B46: General Store | C46: Grain or Water | D46: N/A | E46: N/A — resold directly (see Resources tab) | F46: —
A47: Meal | B47: Tavern | C47: Grain + Water | D47: =Resources!D6+Resources!D5 -> 3 | E47: 10 | F47: =E47-D47 -> 7
A49: Note: Camel/Horse input cost assumes a stated feed-quantity estimate — raising time isn't otherwise modeled. Food (resale) intentionally has no separate final-good price. Armor rows show cost/price for ONE representative piece per tier (Head shown) — Chest and Legs use the same input types at different base prices; see the Armor tab for all nine pieces individually. 2-Horse Chariot uses no Iron (lighter build); 4-Horse Chariot adds Iron reinforcement, matching its higher price and 'strongest' billing.

Sheet Research
A1: Research — Business-Level Investment (Speed & Quality, Never Recipes)
A2: A hired Researcher generates Research Points (RP) for their business over time — base rate on the Assumptions tab, subject to the SAME diminishing-returns decay as production employees (see Businesses tab), tracked as a separate headcount pool from production staff. No cap on Researcher count. The owner spends accumulated RP on either track below. Research NEVER changes what a recipe requires — only how fast a business produces, and how strong its crafted output is. Applies to all businesses except Private Security Contractor and Insurance Brokerage.
A4: THE TWO TRACKS
A5: Efficiency | B5: Speeds up this business's mining/farming/refining/crafting time. Stacks with the +40%/employee speed bonus (Assumptions tab).
A6: Quality | B6: Improves the stats of crafted output without changing input requirements. Each tier grants a total bonus POOL — the crafting business allocates it across whichever stats are available to that item's category (see 'Quality Bonus Stat Pools' below), either all into one stat or split. A Weaponsmith could craft one sword that's all-speed and another that's all-damage, from the same Tier.
A8: RESEARCH TIERS
A9: Tier | B9: Cumulative RP Required | C9: Hours (1 Researcher, at RP rate above) | D9: Efficiency Bonus | E9: Quality Bonus | F9: Quality Tag
A10: Tier 1 | B10: 150 | C10: =B10/Assumptions!C20 -> 18.75 | D10: 0.05 | E10: 0.05 | F10: —
A11: Tier 2 | B11: 400 | C11: =B11/Assumptions!C20 -> 50 | D11: 0.1 | E11: 0.1 | F11: —
A12: Tier 3 | B12: 900 | C12: =B12/Assumptions!C20 -> 112.5 | D12: 0.15 | E12: 0.15 | F12: Fine
A13: Tier 4 | B13: 1800 | C13: =B13/Assumptions!C20 -> 225 | D13: 0.2 | E13: 0.2 | F13: Masterwork
A14: Tier 5 | B14: 3500 | C14: =B14/Assumptions!C20 -> 437.5 | D14: 0.25 | E14: 0.25 | F14: Legendary Craftsmanship
A16: WHY THIS DOESN'T CHANGE RECIPES
A17: A Weaponsmith at Tier 4 Quality still needs exactly 'Bronze + Wood' to craft a Bronze Sword — the Production Chain tab's input costs are untouched. What changes is that the sword it produces deals +20% damage and carries a visible 'Masterwork' tag, making it a real status item without needing a separate Epic/Legendary cosmetic catalog to be built. Efficiency research similarly never reduces how much Bronze or Wood a craft consumes — only how long it takes.
A19: MATERIAL CONSUMPTION DURING RESEARCH (per hour, on top of wages)
A20: A Researcher doesn't just cost wages — they burn a small quantity of the business's own material while testing techniques. This is separate from, and never touches, the crafting recipes on the Production Chain tab. Rate is a stated assumption (units/hour), flat regardless of Research tier.
A21: Business | B21: Test Material | C21: Consumption Rate (units/hr) | D21: Material Cost/hr | E21: Total Hourly Cost (NPC Researcher) | F21: Total Hourly Cost (Player Researcher, Smart Wage)
A22: =Businesses!A5 -> Mining Operation | B22: Wood | C22: 0.5 | D22: =C22*Resources!D7 -> 1 | E22: =D22+Wages!B12 -> 76 | F22: =D22+Wages!C12 -> 34.333333
A23: =Businesses!A6 -> Farm | B23: Grain | C23: 0.5 | D23: =C23*Resources!D6 -> 1 | E23: =D23+Wages!B12 -> 76 | F23: =D23+Wages!C12 -> 34.333333
A24: =Businesses!A7 -> Refinery | B24: Charcoal | C24: 0.5 | D24: =C24*Resources!D10 -> 2 | E24: =D24+Wages!B12 -> 77 | F24: =D24+Wages!C12 -> 35.333333
A25: =Businesses!A8 -> General Store | B25: Wood | C25: 0.3 | D25: =C25*Resources!D7 -> 0.6 | E25: =D25+Wages!B12 -> 75.6 | F25: =D25+Wages!C12 -> 33.933333
A26: =Businesses!A9 -> Home Improvement Store | B26: Stone | C26: 0.5 | D26: =C26*Resources!D8 -> 1.5 | E26: =D26+Wages!B12 -> 76.5 | F26: =D26+Wages!C12 -> 34.833333
A27: =Businesses!A10 -> Mining/Farming Equipment Store | B27: Wood | C27: 0.5 | D27: =C27*Resources!D7 -> 1 | E27: =D27+Wages!B12 -> 76 | F27: =D27+Wages!C12 -> 34.333333
A28: =Businesses!A11 -> Weaponsmith / Armory | B28: Bronze | C28: 0.3 | D28: =C28*Resources!D9 -> 0.6 | E28: =D28+Wages!B12 -> 75.6 | F28: =D28+Wages!C12 -> 33.933333
A29: =Businesses!A12 -> Vehicle Dealer / Stable | B29: Tanned Leather | C29: 0.3 | D29: =C29*Resources!D11 -> 1.8 | E29: =D29+Wages!B12 -> 76.8 | F29: =D29+Wages!C12 -> 35.133333
A30: =Businesses!A13 -> Tavern / Inn | B30: Grain | C30: 0.5 | D30: =C30*Resources!D6 -> 1 | E30: =D30+Wages!B12 -> 76 | F30: =D30+Wages!C12 -> 34.333333
A32: QUALITY BONUS STAT POOLS — WHAT EACH CATEGORY CAN ALLOCATE INTO
A33: Category | B33: Items | C33: Available Stats (tier's % pool splits across these)
A34: Melee Weapons | B34: Wooden Spear, Bronze/Iron Dagger, Bronze/Iron-Tipped Spear, Bronze/Iron Sword | C34: Attack Speed, Damage
A35: Ranged Weapons | B35: Slingshot, Sling, Bow | C35: Attack Speed, Damage, Accuracy
A36: Armor | B36: Leather / Bronze / Iron Head, Chest, Legs | C36: Damage Reduction, Inventory Capacity
A37: Vehicles | B37: Camel, Horse, Donkey Cart, 2-Horse Chariot, 4-Horse Chariot | C37: Cargo Capacity, Speed, Damage Resistance
A38: Food (Tavern Meals) | B38: Base Meal, Tier 1-5 Bread | C38: Sustenance Duration — uses its OWN fixed hour table (12/15/18/21/24/30 hrs), not the generic 5/10/15/20/25% pool used by other categories. See Sustenance tab for the full table and status effects.
A39: HYPOTHETICAL UPGRADE EXAMPLES — ONE ILLUSTRATIVE ITEM PER TIER PER CATEGORY
A40: These are examples of how a business might choose to allocate its pool, not the only valid split. Base item stats (from Weapons/Vehicles/Armor tabs) are unaffected — this is the bonus layered on top.
A41: Tier | B41: Category | C41: Example Name | D41: Base Item | E41: Stat Allocation
A42: Tier 1 (5%) | B42: Melee | C42: Sharpened Bronze Sword | D42: Bronze Sword | E42: +5% Damage
A43: Tier 2 (10%) | B43: Melee | C43: Swift Bronze Dagger | D43: Bronze Dagger | E43: +10% Attack Speed
A44: Tier 3 — Fine (15%) | B44: Melee | C44: Fine Bronze-Tipped Spear | D44: Bronze-Tipped Spear | E44: +8% Damage / +7% Attack Speed
A45: Tier 4 — Masterwork (20%) | B45: Melee | C45: Swift Masterwork Iron Sword | D45: Iron Sword | E45: +20% Attack Speed
A46: Tier 5 — Legendary (25%) | B46: Melee | C46: Legendary Iron Sword | D46: Iron Sword | E46: +25% Damage
A47: Tier 1 (5%) | B47: Ranged | C47: Sharpened Sling | D47: Sling | E47: +5% Damage
A48: Tier 2 (10%) | B48: Ranged | C48: Quick Bow | D48: Bow | E48: +10% Attack Speed
A49: Tier 3 — Fine (15%) | B49: Ranged | C49: Fine Bow | D49: Bow | E49: +15% Accuracy
A50: Tier 4 — Masterwork (20%) | B50: Ranged | C50: Masterwork Bow | D50: Bow | E50: +10% Accuracy / +10% Damage
A51: Tier 5 — Legendary (25%) | B51: Ranged | C51: Legendary Bow | D51: Bow | E51: +9% Accuracy / +8% Damage / +8% Attack Speed
A52: Tier 1 (5%) | B52: Armor | C52: Sturdy Leather Chestpiece | D52: Leather Vest | E52: +5% Damage Reduction
... A61: Tier 5 — Legendary (25%) | B61: Vehicle | C61: Legendary 4-Horse Chariot | D61: 4-Horse Chariot | E61: +25% Cargo Capacity
A63: KNOWN TENSION — UNCAPPED RESEARCHERS VS. INTENDED RESEARCH PACING
A64: Tier 5 (3,500 RP) was paced assuming ONE Researcher (437.5 hours). With uncapped hiring, a business staffing 19 Researchers (the same output-peak point as production labor) generates ~60.4 RP/hour — reaching Tier 5 in roughly 58 hours, well inside a 120-hour run. This means a wealthy business could realistically rush-fund Legendary Craftsmanship items much faster than the original single-Researcher design intended. This is left intentional rather than re-capped — it's a legitimate, dramatic outcome worth observing in the validation run, not a bug to pre-solve. Watch for it specifically when reviewing results: is 'a monopoly rush-funded Legendary gear in week one' an exciting story, or does it need a slower curve after seeing it happen once?

Sheet Armor
A1: Armor — Leather, Bronze & Iron
A2: Three slots (Head/Chest/Legs) stack additively. A full Bronze set totals -40% damage taken; a full Iron set totals -55%. NPC Sell Price uses the same Weaponsmith/Armory markup as weapons. Quality Research (see Research tab) adds a further stat bonus on top of these base values without changing these recipes.
A4: Armor Piece | B4: Slot | C4: Tier | D4: Damage Reduction | E4: Inputs Required | F4: Base Price | G4: NPC Sell Price (Weaponsmith)
A5: Leather Cap | B5: Head | C5: Leather | D5: -0.05 | E5: Tanned Leather | F5: 80 | G5: =F5*Assumptions!C11 -> 136
A6: Leather Vest | B6: Chest | C6: Leather | D6: -0.1 | E6: Tanned Leather | F6: 150 | G6: =F6*Assumptions!C11 -> 255
A7: Leather Leggings | B7: Legs | C7: Leather | D7: -0.05 | E7: Tanned Leather | F7: 80 | G7: =F7*Assumptions!C11 -> 136
A8: Bronze Helm | B8: Head | C8: Bronze | D8: -0.1 | E8: Bronze + Tanned Leather | F8: 300 | G8: =F8*Assumptions!C11 -> 510
A9: Bronze Cuirass | B9: Chest | C9: Bronze | D9: -0.2 | E9: Bronze + Tanned Leather | F9: 550 | G9: =F9*Assumptions!C11 -> 935
A10: Bronze Greaves | B10: Legs | C10: Bronze | D10: -0.1 | E10: Bronze + Tanned Leather | F10: 300 | G10: =F10*Assumptions!C11 -> 510
A11: Iron Helm | B11: Head | C11: Iron | D11: -0.15 | E11: Iron + Tanned Leather | F11: 500 | G11: =F11*Assumptions!C11 -> 850
A12: Iron Cuirass | B12: Chest | C12: Iron | D12: -0.25 | E12: Iron + Tanned Leather | F12: 900 | G12: =F12*Assumptions!C11 -> 1530
A13: Iron Greaves | B13: Legs | C13: Iron | D13: -0.15 | E13: Iron + Tanned Leather | F13: 500 | G13: =F13*Assumptions!C11 -> 850

Sheet Vehicles
A1: Vehicles — Bronze & Iron
A2: NPC Sell Price auto-calculates from Assumptions tab (Government Stables markup). Cargo Capacity is in real units (matches the 'units' resource prices are quoted in) — Donkey Cart is the 100-unit baseline everything else scales against.
A4: Vehicle | B4: Rarity | C4: Speed | D4: Cargo Capacity (units) | E4: Armor | F4: Base Price | G4: NPC Sell Price (Stables)
A5: On Foot (backpack) | B5: Common | C5: Slowest | D5: 5 | E5: None | F5: 0 | G5: =F5*Assumptions!C12 -> 0
A6: Camel | B6: Common | C6: Slow | D6: 20 | E6: None | F6: 150 | G6: =F6*Assumptions!C12 -> 225
A7: Horse | B7: Common | C7: Medium | D7: 15 | E7: None | F7: 200 | G7: =F7*Assumptions!C12 -> 300
A8: Donkey Cart | B8: Uncommon | C8: Slow | D8: 100 | E8: None | F8: 400 | G8: =F8*Assumptions!C12 -> 600
A9: 2-Horse Chariot | B9: Rare | C9: Fast | D9: 80 | E9: Light | F9: 700 | G9: =F9*Assumptions!C12 -> 1050
A10: 4-Horse Chariot | B10: Rare | C10: Fastest | D10: 200 | E10: Medium | F10: 1600 | G10: =F10*Assumptions!C12 -> 2400

Sheet Weapons
A1: Weapons — Bronze & Iron
A2: NPC Sell Price auto-calculates from Assumptions tab (Government Weaponsmith markup). Damage is against 100 HP, unarmored. Hits to Kill is a live formula — edit Damage and it recalculates.
A4: Weapon | B4: Rarity | C4: Type | D4: Damage | E4: Base Price | F4: NPC Sell Price (Weaponsmith) | G4: Attack Speed | H4: Headshot / Backstab | I4: Hits to Kill (unarmored, 100 HP)
A5: Slingshot | B5: Common | C5: Ranged (starter) | D5: 10 | E5: 0 | F5: =E5*Assumptions!C11 -> 0 | G5: 1 per 0.9s | H5: 2x headshot | I5: =ROUNDUP(100/D5,0) -> 10
A6: Sling | B6: Common | C6: Ranged | D6: 14 | E6: 50 | F6: =E6*Assumptions!C11 -> 85 | G6: 1 per 0.8s | H6: 2x headshot | I6: =ROUNDUP(100/D6,0) -> 8
A7: Wooden Spear | B7: Common | C7: Melee | D7: 22 | E7: 60 | F7: =E7*Assumptions!C11 -> 102 | G7: 1 per 0.7s | H7: 1.5x backstab | I7: =ROUNDUP(100/D7,0) -> 5
A8: Bronze Dagger | B8: Uncommon | C8: Melee | D8: 16 | E8: 120 | F8: =E8*Assumptions!C11 -> 204 | G8: 1 per 0.4s | H8: 1.5x backstab | I8: =ROUNDUP(100/D8,0) -> 7
A9: Bronze-Tipped Spear | B9: Uncommon | C9: Melee | D9: 28 | E9: 220 | F9: =E9*Assumptions!C11 -> 374 | G9: 1 per 0.75s | H9: 1.5x backstab | I9: =ROUNDUP(100/D9,0) -> 4
A10: Bronze Sword | B10: Uncommon | C10: Melee | D10: 34 | E10: 250 | F10: =E10*Assumptions!C11 -> 425 | G10: 1 per 0.6s | H10: 1.5x backstab | I10: =ROUNDUP(100/D10,0) -> 3
A11: Bow | B11: Rare | C11: Ranged | D11: 20 | E11: 300 | F11: =E11*Assumptions!C11 -> 510 | G11: 1 per 0.85s | H11: 2x headshot | I11: =ROUNDUP(100/D11,0) -> 5
A12: Iron Dagger | B12: Rare | C12: Melee | D12: 24 | E12: 350 | F12: =E12*Assumptions!C11 -> 595 | G12: 1 per 0.4s | H12: 1.5x backstab | I12: =ROUNDUP(100/D12,0) -> 5
A13: Iron-Tipped Spear | B13: Rare | C13: Melee | D13: 36 | E13: 550 | F13: =E13*Assumptions!C11 -> 935 | G13: 1 per 0.75s | H13: 1.5x backstab | I13: =ROUNDUP(100/D13,0) -> 3
A14: Iron Sword | B14: Rare | C14: Melee | D14: 50 | E14: 650 | F14: =E14*Assumptions!C11 -> 1105 | G14: 1 per 0.6s | H14: 1.5x backstab | I14: =ROUNDUP(100/D14,0) -> 2

Sheet Businesses
A1: Bronze & Iron Age Businesses
A2: Startup Cost is an input (blue). EVERY player-owned business except Insurance Brokerage requires at least one active worker — owner or employee — to produce/operate at all; zero workers = zero output for that period. NO CAP on employee count — output scales via diminishing returns instead of a hard ceiling (see table below). GOVERNMENT-owned businesses are the one exception: always considered fully staffed regardless of actual hires. Owner can personally cover exactly one shift across their entire portfolio. Insurance Brokerage needs capital reserve instead of labor.
A4: Business | B4: Startup Cost | C4: Income Model | D4: Employees Required? | E4: Max Employees | F4: Notes
A5: Mining Operation | B5: 350 | C5: Sells raw resources (ore/wood/stone/clay) to Refinery or Trading Post | D5: Required — zero output with no active worker (owner can self-staff) | E5: Uncapped | F5: Owner counts as a worker if personally staffing it. Output scales with worker count/skill, zero at zero workers. Can hire a Researcher.
A6: Farm | B6: 300 | C6: Sells Water/Grain/Hide/Wool to Trading Post or Tavern | D6: Required — zero output with no active worker (owner can self-staff) | E6: Uncapped | F6: Owner counts as a worker if personally staffing it. Output scales with worker count/skill, zero at zero workers. Can hire a Researcher.
A7: Refinery | B7: 900 | C7: Buys raw resources, sells refined goods (Bronze, Iron, Charcoal, Tanned Leather) at markup | D7: Required — zero output with no active worker (owner can self-staff) | E7: Uncapped | F7: Owner counts as a worker if personally staffing it. Output scales with worker count/skill, zero at zero workers. Can hire a Researcher.
A8: General Store | B8: 500 | C8: Buys/sells common goods at player-set retail markup | D8: Required for extended hours | E8: 2 | F8: 1 shift free (owner), 2 more shifts need employees. Can hire a Researcher.
A9: Home Improvement Store | B9: 500 | C9: Buys Stone/Clay/Wood, assembles and sells Property Upgrades | D9: Required for extended hours | E9: 2 | F9: Can hire a Researcher.
A10: Mining/Farming Equipment Store | B10: 550 | C10: Buys Wood/Bronze, assembles and sells Upgraded Tools | D10: Required for extended hours | E10: 2 | F10: Can hire a Researcher.
A11: Weaponsmith / Armory | B11: 700 | C11: Buys refined goods, assembles and sells weapons and armor (all tiers) at markup | D11: Required for extended hours | E11: 2 | F11: Blacksmith employee also speeds crafting. Can hire a Researcher.
A12: Vehicle Dealer / Stable | B12: 600 | C12: Sells/raises Camels/Horses; assembles and sells Donkey Carts and Chariots | D12: Required for extended hours | E12: 2 | F12: Can hire a Researcher.
A13: Tavern / Inn | B13: 400 | C13: Sells meals — see Sustenance tab for pricing and Research-driven duration tiers | D13: Required for extended hours | E13: 2 | F13: Alternative to self-prepared Grain+Water. Research (Quality track) unlocks higher-tier breads with longer Sustenance Duration — see Sustenance and Research tabs. Higher tier = higher price. Can hire a Researcher.
A14: Private Security Contractor | B14: 1000 | C14: Supplies hired guards to convoys; takes a cut of guard pay | D14: Guards ARE the employees | E14: N/A | F14: No separate staffing beyond the guards themselves. No Research track.
A15: Insurance Brokerage | B15: 1500 | C15: Sells cargo/vehicle policies; pays out claims | D15: None — capital reserve instead | E15: 0 | F15: No employees needed. Must maintain cash reserve ≥ 70% of total outstanding insured value to issue new policies (matches the 70% payout rate). Funded by owner capital and/or investors — pitched and negotiated directly in chat, revenue-share terms set between the parties. See Government & Insurance tab.
A17: DIMINISHING RETURNS — HOW OUTPUT SCALES WITH EMPLOYEE COUNT (uncapped, no hard ceiling)
A18: Each additional employee reduces every worker's individual rate by 5%, compounding: Per-Worker Rate at n employees = Base Rate × Skill Multiplier × 0.95^(n-1). Total Business Output = n × Per-Worker Rate. This applies to production employees AND Researchers, tracked as SEPARATE headcount pools — a business can staff both simultaneously, each decaying against only its own pool. No hard cap on either pool; the math itself creates a natural soft ceiling instead (see table below).
A19: Employees (n) | B19: Per-Worker Rate (% of base) | C19: Total Output Multiplier
A20: 1 | B20: 1 | C20: 1.000x
A21: 2 | B21: 0.95 | C21: 1.900x
A22: 3 | B22: 0.9025 | C22: 2.708x
A23: 4 | B23: 0.8574 | C23: 3.429x
A24: 5 | B24: 0.8145 | C24: 4.073x
A25: 10 | B25: 0.6302 | C25: 6.302x
A26: 15 | B26: 0.4877 | C26: 7.315x
A27: 19 | B27: 0.3972 | C27: 7.547x
A28: 20 | B28: 0.3774 | C28: 7.547x
A29: 25 | B29: 0.292 | C29: 7.300x
A30: 30 | B30: 0.2259 | C30: 6.778x
A32: Total output PEAKS at n=19-20 (≈7.55x a single worker) and then declines — past ~20 employees, hiring more people actively hurts total output, not just per-worker efficiency. This is why no hard cap is needed: the formula creates its own soft ceiling around 20 workers per pool without an arbitrary rule. A monopoly can still dominate — it does so by owning MULTIPLE businesses near their individual peaks, or by investing in Research's Efficiency track (uncapped, hours-driven, stacks on top of this), not by mass-hiring into one location.
A33: Worked example — Iron, 3 Refinery Workers, Novice skill: Base Rate 15/hr (Resources tab) × 0.9025 (3-worker decay) = 13.54/hr per worker × 3 workers = 40.6 Iron/hour total. At Base Price 22/unit (Resources tab), that's roughly $893/hour of Iron produced before wages, input costs, or the NPC buy/sell spread are applied.

Sheet Wages
A1: Wages (per real-time hour)
A2: NPC Wage is an input (blue). Smart Player Wage and Minimum Wage Floor auto-calculate from Assumptions tab.
A4: Role | B4: NPC Employee Wage/hr | C4: Smart Player Wage/hr (recommended) | D4: Minimum Wage Floor/hr (enforced) | E4: Used In
A5: Laborer | B5: 45 | C5: =B5/Assumptions!C15 -> 20 | D5: =C5*Assumptions!C16 -> 10 | E5: Mining Operation, Farm
A6: Miner (uncommon ore) | B6: 65 | C6: =B6/Assumptions!C15 -> 28.888889 | D6: =C6*Assumptions!C16 -> 14.444444 | E6: Mining Operation
A7: Farmhand | B7: 50 | C7: =B7/Assumptions!C15 -> 22.222222 | D7: =C7*Assumptions!C16 -> 11.111111 | E7: Farm
A8: Refinery Worker | B8: 85 | C8: =B8/Assumptions!C15 -> 37.777778 | D8: =C8*Assumptions!C16 -> 18.888889 | E8: Refinery
A9: Store Clerk | B9: 40 | C9: =B9/Assumptions!C15 -> 17.777778 | D9: =C9*Assumptions!C16 -> 8.8888889 | E9: General Store, Home Improvement Store, Equipment Store, Vehicle Dealer, Tavern
A10: Blacksmith | B10: 80 | C10: =B10/Assumptions!C15 -> 35.555556 | D10: =C10*Assumptions!C16 -> 17.777778 | E10: Weaponsmith / Armory
A11: Stablehand | B11: 45 | C11: =B11/Assumptions!C15 -> 20 | D11: =C11*Assumptions!C16 -> 10 | E11: Vehicle Dealer / Stable
A12: Researcher | B12: 75 | C12: =B12/Assumptions!C15 -> 33.333333 | D12: =C12*Assumptions!C16 -> 16.666667 | E12: Any business except Private Security Contractor / Insurance Brokerage — see Research tab
A15: SKILL PROGRESSION (per role name, tracked across all businesses)
A16: Speed only — Research already owns the quality bonus at the business level, so personal skill stays scoped to how fast an individual works. XP = cumulative hours actively worked at that role name, shared across every business of that type (e.g., hours as Laborer at a Mine and at a Farm add together).
A17: Tier | B17: Cumulative Hours Worked | C17: Speed Bonus
A18: Novice | B18: 0 - 4 | C18: 0
A19: Journeyman | B19: 5 - 14 | C19: 0.1
A20: Skilled | B20: 15 - 34 | C20: 0.2
A21: Expert | B21: 35 - 69 | C21: 0.35
A22: Master | B22: 70+ | C22: 0.5
A24: Stacks additively with employee-count bonus and Research's Efficiency bonus. Applies to all 8 wage roles, including Researcher — a skilled Researcher generates more RP/hour, not just faster labor.

Sheet Progression Math
A1: Progression Math — Hours of Labor to Afford Key Purchases
A2: Shows how many real-time hours of work (at each wage tier) it takes to save for each item. Recalculates automatically from Wages, Vehicles, Weapons, Armor, and Businesses tabs.
A4: Item | B4: Cost | C4: Hrs @ Laborer Wage (Smart Rate) | D4: Hrs @ Refinery Worker Wage (Smart Rate) | E4: Hrs @ NPC Laborer Wage (for comparison)
A5: VEHICLES (Base Price)
A6: On Foot (backpack) | B6: =Vehicles!F5 -> 0 | C6: =IF(Wages!C5=0,0,B6/Wages!C5) -> 0 | D6: =IF(Wages!C8=0,0,B6/Wages!C8) -> 0 | E6: =IF(Wages!B5=0,0,B6/Wages!B5) -> 0
A7: Camel | B7: =Vehicles!F6 -> 150 | C7: =IF(Wages!C5=0,0,B7/Wages!C5) -> 7.5 | D7: =IF(Wages!C8=0,0,B7/Wages!C8) -> 3.9705882 | E7: =IF(Wages!B5=0,0,B7/Wages!B5) -> 3.3333333
A8: Horse | B8: =Vehicles!F7 -> 200 | C8: =IF(Wages!C5=0,0,B8/Wages!C5) -> 10 | D8: =IF(Wages!C8=0,0,B8/Wages!C8) -> 5.2941176 | E8: =IF(Wages!B5=0,0,B8/Wages!B5) -> 4.4444444
A9: Donkey Cart | B9: =Vehicles!F8 -> 400 | C9: =IF(Wages!C5=0,0,B9/Wages!C5) -> 20 | D9: =IF(Wages!C8=0,0,B9/Wages!C8) -> 10.588235 | E9: =IF(Wages!B5=0,0,B9/Wages!B5) -> 8.8888889
A10: 2-Horse Chariot | B10: =Vehicles!F9 -> 700 | C10: =IF(Wages!C5=0,0,B10/Wages!C5) -> 35 | D10: =IF(Wages!C8=0,0,B10/Wages!C8) -> 18.529412 | E10: =IF(Wages!B5=0,0,B10/Wages!B5) -> 15.555556
A11: 4-Horse Chariot | B11: =Vehicles!F10 -> 1600 | C11: =IF(Wages!C5=0,0,B11/Wages!C5) -> 80 | D11: =IF(Wages!C8=0,0,B11/Wages!C8) -> 42.352941 | E11: =IF(Wages!B5=0,0,B11/Wages!B5) -> 35.555556
A13: WEAPONS (Base Price)
A14: Slingshot | B14: =Weapons!E5 -> 0 | C14: =IF(Wages!C5=0,0,B14/Wages!C5) -> 0 | D14: =IF(Wages!C8=0,0,B14/Wages!C8) -> 0 | E14: =IF(Wages!B5=0,0,B14/Wages!B5) -> 0
A15: Sling | B15: =Weapons!E6 -> 50 | C15: =IF(Wages!C5=0,0,B15/Wages!C5) -> 2.5 | D15: =IF(Wages!C8=0,0,B15/Wages!C8) -> 1.3235294 | E15: =IF(Wages!B5=0,0,B15/Wages!B5) -> 1.1111111
A16: Wooden Spear | B16: =Weapons!E7 -> 60 | C16: =IF(Wages!C5=0,0,B16/Wages!C5) -> 3 | D16: =IF(Wages!C8=0,0,B16/Wages!C8) -> 1.5882353 | E16: =IF(Wages!B5=0,0,B16/Wages!B5) -> 1.3333333
A17: Bronze Dagger | B17: =Weapons!E8 -> 120 | C17: =IF(Wages!C5=0,0,B17/Wages!C5) -> 6 | D17: =IF(Wages!C8=0,0,B17/Wages!C8) -> 3.1764706 | E17: =IF(Wages!B5=0,0,B17/Wages!B5) -> 2.6666667
A18: Bronze-Tipped Spear | B18: =Weapons!E9 -> 220 | C18: =IF(Wages!C5=0,0,B18/Wages!C5) -> 11 | D18: =IF(Wages!C8=0,0,B18/Wages!C8) -> 5.8235294 | E18: =IF(Wages!B5=0,0,B18/Wages!B5) -> 4.8888889
A19: Bronze Sword | B19: =Weapons!E10 -> 250 | C19: =IF(Wages!C5=0,0,B19/Wages!C5) -> 12.5 | D19: =IF(Wages!C8=0,0,B19/Wages!C8) -> 6.6176471 | E19: =IF(Wages!B5=0,0,B19/Wages!B5) -> 5.5555556
A20: Bow | B20: =Weapons!E11 -> 300 | C20: =IF(Wages!C5=0,0,B20/Wages!C5) -> 15 | D20: =IF(Wages!C8=0,0,B20/Wages!C8) -> 7.9411765 | E20: =IF(Wages!B5=0,0,B20/Wages!B5) -> 6.6666667
A21: Iron Dagger | B21: =Weapons!E12 -> 350 | C21: =IF(Wages!C5=0,0,B21/Wages!C5) -> 17.5 | D21: =IF(Wages!C8=0,0,B21/Wages!C8) -> 9.2647059 | E21: =IF(Wages!B5=0,0,B21/Wages!B5) -> 7.7777778
A22: Iron-Tipped Spear | B22: =Weapons!E13 -> 550 | C22: =IF(Wages!C5=0,0,B22/Wages!C5) -> 27.5 | D22: =IF(Wages!C8=0,0,B22/Wages!C8) -> 14.558824 | E22: =IF(Wages!B5=0,0,B22/Wages!B5) -> 12.222222
A23: Iron Sword | B23: =Weapons!E14 -> 650 | C23: =IF(Wages!C5=0,0,B23/Wages!C5) -> 32.5 | D23: =IF(Wages!C8=0,0,B23/Wages!C8) -> 17.205882 | E23: =IF(Wages!B5=0,0,B23/Wages!B5) -> 14.444444
A25: ARMOR (Base Price)
A26: Leather Cap | B26: =Armor!F5 -> 80 | C26: =IF(Wages!C5=0,0,B26/Wages!C5) -> 4 | D26: =IF(Wages!C8=0,0,B26/Wages!C8) -> 2.1176471 | E26: =IF(Wages!B5=0,0,B26/Wages!B5) -> 1.7777778
A27: Leather Vest | B27: =Armor!F6 -> 150 | C27: =IF(Wages!C5=0,0,B27/Wages!C5) -> 7.5 | D27: =IF(Wages!C8=0,0,B27/Wages!C8) -> 3.9705882 | E27: =IF(Wages!B5=0,0,B27/Wages!B5) -> 3.3333333
A28: Leather Leggings | B28: =Armor!F7 -> 80 | C28: =IF(Wages!C5=0,0,B28/Wages!C5) -> 4 | D28: =IF(Wages!C8=0,0,B28/Wages!C8) -> 2.1176471 | E28: =IF(Wages!B5=0,0,B28/Wages!B5) -> 1.7777778
A29: Bronze Helm | B29: =Armor!F8 -> 300 | C29: =IF(Wages!C5=0,0,B29/Wages!C5) -> 15 | D29: =IF(Wages!C8=0,0,B29/Wages!C8) -> 7.9411765 | E29: =IF(Wages!B5=0,0,B29/Wages!B5) -> 6.6666667
A30: Bronze Cuirass | B30: =Armor!F9 -> 550 | C30: =IF(Wages!C5=0,0,B30/Wages!C5) -> 27.5 | D30: =IF(Wages!C8=0,0,B30/Wages!C8) -> 14.558824 | E30: =IF(Wages!B5=0,0,B30/Wages!B5) -> 12.222222
A31: Bronze Greaves | B31: =Armor!F10 -> 300 | C31: =IF(Wages!C5=0,0,B31/Wages!C5) -> 15 | D31: =IF(Wages!C8=0,0,B31/Wages!C8) -> 7.9411765 | E31: =IF(Wages!B5=0,0,B31/Wages!B5) -> 6.6666667
A32: Iron Helm | B32: =Armor!F11 -> 500 | C32: =IF(Wages!C5=0,0,B32/Wages!C5) -> 25 | D32: =IF(Wages!C8=0,0,B32/Wages!C8) -> 13.235294 | E32: =IF(Wages!B5=0,0,B32/Wages!B5) -> 11.111111
A33: Iron Cuirass | B33: =Armor!F12 -> 900 | C33: =IF(Wages!C5=0,0,B33/Wages!C5) -> 45 | D33: =IF(Wages!C8=0,0,B33/Wages!C8) -> 23.823529 | E33: =IF(Wages!B5=0,0,B33/Wages!B5) -> 20
A34: Iron Greaves | B34: =Armor!F13 -> 500 | C34: =IF(Wages!C5=0,0,B34/Wages!C5) -> 25 | D34: =IF(Wages!C8=0,0,B34/Wages!C8) -> 13.235294 | E34: =IF(Wages!B5=0,0,B34/Wages!B5) -> 11.111111
A36: BUSINESSES (Startup Cost)
A37: =Businesses!A5 -> Mining Operation | B37: =Businesses!B5 -> 350 | C37: =IF(Wages!C5=0,0,B37/Wages!C5) -> 17.5 | D37: =IF(Wages!C8=0,0,B37/Wages!C8) -> 9.2647059 | E37: =IF(Wages!B5=0,0,B37/Wages!B5) -> 7.7777778
A38: =Businesses!A6 -> Farm | B38: =Businesses!B6 -> 300 | C38: =IF(Wages!C5=0,0,B38/Wages!C5) -> 15 | D38: =IF(Wages!C8=0,0,B38/Wages!C8) -> 7.9411765 | E38: =IF(Wages!B5=0,0,B38/Wages!B5) -> 6.6666667
A39: =Businesses!A7 -> Refinery | B39: =Businesses!B7 -> 900 | C39: =IF(Wages!C5=0,0,B39/Wages!C5) -> 45 | D39: =IF(Wages!C8=0,0,B39/Wages!C8) -> 23.823529 | E39: =IF(Wages!B5=0,0,B39/Wages!B5) -> 20
A40: =Businesses!A8 -> General Store | B40: =Businesses!B8 -> 500 | C40: =IF(Wages!C5=0,0,B40/Wages!C5) -> 25 | D40: =IF(Wages!C8=0,0,B40/Wages!C8) -> 13.235294 | E40: =IF(Wages!B5=0,0,B40/Wages!B5) -> 11.111111
A41: =Businesses!A9 -> Home Improvement Store | B41: =Businesses!B9 -> 500 | C41: =IF(Wages!C5=0,0,B41/Wages!C5) -> 25 | D41: =IF(Wages!C8=0,0,B41/Wages!C8) -> 13.235294 | E41: =IF(Wages!B5=0,0,B41/Wages!B5) -> 11.111111
A42: =Businesses!A10 -> Mining/Farming Equipment Store | B42: =Businesses!B10 -> 550 | C42: =IF(Wages!C5=0,0,B42/Wages!C5) -> 27.5 | D42: =IF(Wages!C8=0,0,B42/Wages!C8) -> 14.558824 | E42: =IF(Wages!B5=0,0,B42/Wages!B5) -> 12.222222
A43: =Businesses!A11 -> Weaponsmith / Armory | B43: =Businesses!B11 -> 700 | C43: =IF(Wages!C5=0,0,B43/Wages!C5) -> 35 | D43: =IF(Wages!C8=0,0,B43/Wages!C8) -> 18.529412 | E43: =IF(Wages!B5=0,0,B43/Wages!B5) -> 15.555556
A44: =Businesses!A12 -> Vehicle Dealer / Stable | B44: =Businesses!B12 -> 600 | C44: =IF(Wages!C5=0,0,B44/Wages!C5) -> 30 | D44: =IF(Wages!C8=0,0,B44/Wages!C8) -> 15.882353 | E44: =IF(Wages!B5=0,0,B44/Wages!B5) -> 13.333333
A45: =Businesses!A13 -> Tavern / Inn | B45: =Businesses!B13 -> 400 | C45: =IF(Wages!C5=0,0,B45/Wages!C5) -> 20 | D45: =IF(Wages!C8=0,0,B45/Wages!C8) -> 10.588235 | E45: =IF(Wages!B5=0,0,B45/Wages!B5) -> 8.8888889
A46: =Businesses!A14 -> Private Security Contractor | B46: =Businesses!B14 -> 1000 | C46: =IF(Wages!C5=0,0,B46/Wages!C5) -> 50 | D46: =IF(Wages!C8=0,0,B46/Wages!C8) -> 26.470588 | E46: =IF(Wages!B5=0,0,B46/Wages!B5) -> 22.222222
A47: =Businesses!A15 -> Insurance Brokerage | B47: =Businesses!B15 -> 1500 | C47: =IF(Wages!C5=0,0,B47/Wages!C5) -> 75 | D47: =IF(Wages!C8=0,0,B47/Wages!C8) -> 39.705882 | E47: =IF(Wages!B5=0,0,B47/Wages!B5) -> 33.333333
A49: RESEARCH TIERS (Hours of Researcher Employment, Independent of Wage Paid)
A50: Tier 1 | B50: =Research!B10 -> 150 | C50: =Research!C10 -> 18.75 | D50: — | E50: —
A51: Tier 2 | B51: =Research!B11 -> 400 | C51: =Research!C11 -> 50 | D51: — | E51: —
A52: Tier 3 (Fine) | B52: =Research!B12 -> 900 | C52: =Research!C12 -> 112.5 | D52: — | E52: —
A53: Tier 4 (Masterwork) | B53: =Research!B13 -> 1800 | C53: =Research!C13 -> 225 | D53: — | E53: —
A54: Tier 5 (Legendary Craftsmanship) | B54: =Research!B14 -> 3500 | C54: =Research!C14 -> 437.5 | D54: — | E54: —
A56: Note: 'Smart Rate' pulls from the recommended player wage on the Wages tab, not the inflated NPC wage. Research hours are independent of wage paid.
A58: KNOWN BALANCE RISKS — WATCH THESE SPECIFICALLY IN THE VALIDATION RUN
A59: • | B59: Convoy pay vs. mining wages: a Driver earns roughly 17x per-minute what a Laborer earns — intentional, but could pull agents away from mining entirely if the gap proves too strong. Cargo can't exist without someone mining it first.
A60: • | B60: Iron Refinery margin: 3 Refinery Workers producing ~40.6 Iron/hour at $22/unit base price is roughly $893/hour of output before costs — a large number worth checking against real wages and input costs once the run is live, not just trusting the formula in isolation.
A61: • | B61: Researcher rush-funding: uncapped Researcher hiring can reach Research Tier 5 in ~58 hours instead of the 437.5 hours a single-Researcher design assumed — see Research tab for full detail. Not necessarily wrong, but worth watching whether it happens and whether it's a good story or too fast.
A62: • | B62: Diminishing returns peak (~19-20 workers per pool): untested whether agents actually discover this peak and staff toward it, overshoot past it, or never approach it at all — a genuine behavioral question the validation run is specifically positioned to answer.

Sheet Actions
A1: Agent Action / Tool List
A2: Every callable action an agent's turn can consist of. Read access to server-wide and guild chat is available context every turn, not a callable action itself. Skill growth from Mining/Farming/Refining/Crafting is a passive side-effect, not a separate action.
A4: Category | B4: Action | C4: Notes
A5: MOVEMENT
B6: Travel to a location | C6: Time-based, proportional to distance and vehicle speed — no teleportation
B7: Mount / Dismount vehicle
B8: Wait / Idle | C8: Explicit no-op, needed especially for the simplest agent tier
A9: LABOR
B10: Begin mining at a resource node | C10: Passive — runs until stopped, not a repeated per-tick action
B11: Stop mining
B12: Begin farming at a resource node | C12: Passive
B13: Stop farming
B14: Begin a work shift at a business | C14: Passive wage labor
B15: End work shift
B16: Apply for a job
B17: Quit a job
A18: REFINING & CRAFTING
B19: Begin refining at a Refinery | C19: Passive — runs until stopped
B20: Stop refining
B21: Craft a final good | C21: Discrete choice, resolves over time
B22: Choose quality stat allocation when crafting | C22: Only if the business has an unlocked Research tier
A23: TRADING & MARKET
B24: Buy from a business
B25: Sell to a business
B26: Set retail price | C26: Business owner only
B27: Buy an existing business from another player
B28: Direct trade with another player | C28: The only channel for stolen/rare goods — no anonymous black market screen
A29: BUSINESS MANAGEMENT
B30: Start a business
B31: Hire employee
B32: Fire employee
B33: Set wage for a role
B34: Deposit cash into business
B35: Withdraw profit
B36: Sell business to another player
B37: Invest in another player's business | C37: Silent investor, no labor
B38: Hire a Researcher
B39: Allocate Research Points | C39: Efficiency vs Quality track
A40: CONVOY SYSTEM
B41: Post a convoy job | C41: Organizer only — max 1 per rolling hour per business, see Convoy tab
B42: Cancel a posted convoy
B43: Join a convoy | C43: As Driver, Scout, or Bodyguard
B44: Leave a convoy mid-run | C44: Risky
B45: Load cargo onto a convoy
B46: Depart a convoy | C46: Organizer decides to depart short-handed or extend recruiting — see Convoy tab
B47: Actively drive a convoy vehicle
B48: Claim convoy pay / commission | C48: After completion — see Convoy tab for the pay formula
A49: COMBAT
B50: Melee attack | C50: Distinct swing animation for spectator visibility
B51: Ranged attack — quick shot
B52: Ranged attack — charge and release | C52: Bow / Sling
B53: Block / defend | C53: For visual variety
B54: Flee combat
B55: Ram a target with a vehicle
B56: Fight from a moving vehicle
A57: THEFT & CRIME
B58: Steal cargo from a convoy | C58: Hold-to-siphon
B59: Pickpocket another player
B60: Steal an unattended vehicle
B61: Rob an unstaffed business till
B62: Destroy a vehicle
B63: Loot a killed player's dropped items
B64: Loot a convoy wreck
B65: Sabotage | C65: Vandalize a business or refinery
A66: BOUNTY & LAW
B67: Report a witnessed crime
B68: Pay off own bounty at police station
B69: Place a bounty on another player
B70: Hunt an active bounty target
B71: Claim a bounty | C71: After a successful kill
A72: SCOUTING & INTELLIGENCE
B73: Scout ahead of a convoy
B74: Place a location marker | C74: Last-seen sighting, not a live tracker
B75: Report intel to a convoy organizer
B76: Use the tracking shot | C76: Sniper-mark mechanic
B77: Post a decoy convoy
A78: PROPERTY & REAL ESTATE
B79: Buy property | C79: Auction or direct
B80: Sell property
B81: Build a structure | C81: Free-build, resource-gated
B82: Buy a Property Upgrade
B83: Store a vehicle | C83: Garage
B84: Store resources | C84: Home storage
B85: Rent a property from a landlord
B86: Collect rent | C86: Landlord only
A87: GOVERNMENT & POLITICS
B88: Propose a policy | C88: Tax rate, infrastructure funding, etc. — pure direct democracy, no elected office
B89: Co-sign a proposal | C89: Needed to reach the ballot threshold
B90: Vote on a proposal | C90: 2/3 majority required to enact — executes immediately once threshold is reached
B91: Vote to reverse an enacted policy | C91: 2/3 majority required to reverse
A92: ALLIANCES & SOCIAL
B93: Post to server-wide chat
B94: Create a guild
B95: Invite player to guild
B96: Accept guild invite
B97: Leave guild
B98: Remove a guild member | C98: Guild leader only
B99: Post to guild chat | C99: Private to guild members
B100: Form or join a pirate crew
A101: SURVIVAL
...

Sheet Convoy
A1: Convoy System — Roles, Pay Formula & Rules
A2: Pay rates below are the GOVERNMENT BASELINE — used by every government-owned business's convoys. Once a player owns that business, they set their own convoy pay terms when organizing, exactly like player stores set their own retail prices instead of the NPC markup. Cargo is filled before departure by whoever mined/farmed/refined it — Miner is not a role during the transport leg itself.
A4: THE THREE CONVOY ROLES
A5: Driver | B5: Required, one per vehicle in the convoy. Physically hauls the cargo.
A6: Scout | B6: Optional. Rides ahead of the convoy, reduces ambush risk.
A7: Bodyguard | B7: Optional. Rides with the convoy, defends it directly if attacked.
A9: GOVERNMENT BASELINE PAY FORMULA
A10: Role | B10: Flat Fee (Denari) | C10: Commission % | D10: Commission Basis | E10: Notes
A11: Driver — organizer-provided vehicle | B11: 10 | C11: 0.005 | D11: That vehicle's own cargo value | E11: Commission forfeited on failure
A12: Driver — own vehicle | B12: 15 | C12: 0.0075 | D12: That vehicle's own cargo value | E12: Higher rate — compensates for risking a personal asset
A13: Scout | B13: 8 | C13: 0.0025 | D13: Total convoy cargo value | E13: Protects the whole convoy, not just one vehicle
A14: Bodyguard | B14: 8 | C14: 0.0035 | D14: Total convoy cargo value | E14: Protects the whole convoy, not just one vehicle
A16: WORKED EXAMPLE — LIVE, RECALCULATES FROM RESOURCES + RATE TABLE ABOVE
A17: Scenario: 1 Donkey Cart, fully loaded with Bronze, own vehicle, Scout + Bodyguard hired
A18: Cargo Good | B18: Bronze
A19: Cargo Base Price (per unit) | B19: =Resources!D13 -> 18
A20: Quantity Hauled (units) | B20: 100
A21: Total Cargo Value | B21: =B19*B20 -> 1800
A23: Role | B23: Flat Fee | C23: Commission Earned | D23: Total Pay (this run)
A24: Driver (own vehicle) | B24: =B12 -> 15 | C24: =C12*B21 -> 13.5 | D24: =B24+C24 -> 28.5
A25: Scout | B25: =B13 -> 8 | C25: =C13*B21 -> 4.5 | D25: =B25+C25 -> 12.5
A26: Bodyguard | B26: =B14 -> 8 | C26: =C14*B21 -> 6.3 | D26: =B26+C26 -> 14.3
A28: For comparison: 5 minutes of Laborer wages at the Smart Rate (Wages!C5) earns roughly $1.67 — a Driver on this run earns over 17x more per minute than mining, which is the intended gap.
A30: POSTING & RECRUITMENT RULES
A31: • | B31: One new convoy job per organizing business per rolling hour (not a fixed clock reset — 60 minutes from that business's last post).
A32: • | B32: No global convoy cap. Any number of convoys can run simultaneously across the world.
A33: • | B33: Maximum 10 vehicles per convoy. No cap on total crew size (Scouts/Bodyguards) — market and cost are the only limiters.
A34: • | B34: Convoy can depart with just a Driver — Scout and Bodyguard are both fully optional.
A35: • | B35: Initial recruiting window: 15 minutes. If unfilled, the organizer decides: depart short-handed, or extend 15 more minutes — capped at 3 extensions (60 minutes total) before a decision is forced.
A36: • | B36: A business must always be staffed. The owner can only join their own convoy (as Driver, Scout, or Bodyguard) if at least one employee remains covering the shop.
A37: • | B37: If the organizing business goes bankrupt before departure, the convoy is cancelled. A convoy already in transit completes normally regardless of what happens to the business.
A38: • | B38: Agents should weight an available convoy role heavily in their decision-making — convoy pay is designed to far exceed solo Labor wages per minute (see worked example above) — but this is not a hard override; an agent can rationally decline.
A40: When a convoy is ambushed mid-transit, each vehicle's Driver gets a three-way choice (Fight / Push Through / Flee Off-Road), decided independently per vehicle — see Combat & Heroes tab for full detail.

Sheet Government & Insurance
A1: Government, Taxes, Bounties & Insurance
A2: Pure direct democracy — no elected office. Proposals need co-signers to reach the ballot, 2/3 majority to enact, 2/3 to reverse (reversing restores both the service level and its tax delta). Enacted policies execute immediately. All tax rates start at 5% (Assumptions tab) and are bounded 0-25% by any combination of policies.
A4: BUNDLED INFRASTRUCTURE & POLICE POLICIES (move Wage + Sales + Property tax together)
A5: Policy | B5: Effect | C5: Wage/Sales/Property Tax | D5: Notes
A6: Better Roads | B6: Convoy speed +10% | C6: 5% → 6% | D6: Reversible
A7: Less Road Funding | B7: Convoy speed -10% | C7: 5% → 4% | D7: Reversible
A8: New Road Project | B8: Second route exists, harder for pirates to track/predict | C8: 5% → 8% | D8: "Massive" tax increase by design
A9: Police Tier 1 | B9: 60 sec response time, 1 officer | C9: 5% → 6% | D9: No police exist at all until this passes
A10: Police Tier 2 | B10: 45 sec response time, 2 officers (parallel capacity) | C10: 6% → 7% | D10: Cumulative on top of Tier 1
A11: Police Tier 3 | B11: 30 sec response time, 3 officers (parallel capacity) | C11: 7% → 8% | D11: Cumulative on top of Tier 1+2
A13: STANDALONE TAX POLICIES (single tax type, independent of any service)
A14: • | B14: Raise / Lower Wage Tax — ±1% per vote, bounded 0-25%
A15: • | B15: Raise / Lower Sales Tax — ±1% per vote, bounded 0-25%
A16: • | B16: Raise / Lower Property Tax — ±1% per vote, bounded 0-25%
A17: • | B17: Progressive Taxation (toggle) — wage/sales tax scales with agent Net Worth instead of a flat rate for everyone
A19: BOUNTY POLICIES & FORMULA
A20: Higher / Lower Bounties (toggle) | B20: ±50% multiplier applied to all three base bounty amounts below
A22: Crime | B22: Base Bounty | C22: Stacks?
A23: Theft (cargo/pickpocket/till/vehicle) | B23: 25% of stolen value | C23: Yes — each theft adds its own bounty
A24: Murder | B24: 300 Denari | C24: Yes, per instance — 3 murders = 900 Denari total
A25: Sabotage | B25: 150 Denari | C25: Yes — each instance adds its own bounty
A27: CRIME DETECTION — POLICE-WITNESSED ONLY
A28: • | B28: A bounty is only ever confirmed by a POLICE OFFICER witnessing or arriving in time — other agents seeing a crime cannot place a government bounty directly (no 'proof').
A29: • | B29: Any agent can 'Call the police' when a crime occurs, logging a dispatch with location and timestamp.
A30: • | B30: At zero police funding (the default), no bounty is ever possible regardless of witnesses.
A31: • | B31: Once police exist, they must arrive within a 10-minute evidence window from the crime for the bounty to be confirmed. A stale report (police too slow, or busy with another dispatch) means no bounty.
A32: • | B32: Police capacity is parallel by tier (1/2/3 simultaneous dispatches) — a real crime wave can overwhelm a low tier even if its response time looks fine on paper.
A33: • | B33: Player-added bounties (funded directly by any agent, uncapped) still stack on top of any confirmed government bounty regardless of police involvement.
A35: INSURANCE PRODUCTS
A36: Product | B36: Protects | C36: Premium (NPC) | D36: Payout | E36: Notes
A37: Cargo / Vehicle-in-Transit | B37: A single convoy run | C37: 20% of insured value | D37: 70% of insured value | E37: Player brokers can undercut to ~8-12%
A38: Life Insurance | B38: Carried Denari + inventory on death | C38: 20% of declared coverage, paid hourly | D38: 70% of coverage on death | E38: Ongoing policy, not per-trip
A39: Asset Insurance | B39: Ownership of vehicle/property/business on death | C39: 20% of combined insured asset value, paid hourly | D39: Guaranteed retention (in-kind, no Denari payout) | E39: Without it: assets become claimable by others 24 hrs after owner's death unless reclaimed first
A41: An Insurance Brokerage (government-owned by default, player-ownable later) must maintain a cash reserve ≥ 70% of its total outstanding insured value to issue new policies — directly derived from the 70% payout rate, ensuring claims can actually be honored.

Sheet World State Schema
A1: World State Schema
A2: The actual data structure every rule in this workbook reads and writes to. Ten entity types, each with the fields an agent's turn (or the daily report generator) needs. This is the reference for building the headless sandbox backend.
A4: 1. AGENT
A5: Field | B5: Type / Format | C5: Notes
A6: Agent ID | B6: unique ID
A7: Name | B7: string
A8: Model / Tier | B8: enum | C8: See Combat & Heroes tab — one of the 5 models in the current roster — see Combat & Heroes tab for the exact list and agent counts
A9: Denari Balance | B9: number | C9: Liquid currency on hand
A10: Net Worth | B10: computed | C10: Denari + owned businesses (startup cost) + vehicles (base price) + property (purchase + upgrades) + inventory (base price). THE wealth-ranking metric — agents' goal is maximizing this by hour 120, not liquid Denari alone
A11: Current Location | B11: named location or transit state | C11: e.g. 'The Crossing' or 'en route: Refinery Row→Town at 40%' — see World entity for the location graph
A12: Inventory | B12: list, max 5 units | C12: Same 5-unit cap whether on foot or mounted on a vehicle
A13: Equipped Weapon | B13: item ref
A14: Equipped Armor | B14: 3 slots: Head/Chest/Legs
A15: Owned Vehicles | B15: list of Vehicle IDs
A16: Owned Businesses | B16: list of Business IDs | C16: Agents can own multiple, limited only by startup cost and staffing (see Business entity)
A17: Owned Property | B17: Property ID or none | C17: Max 1
A18: Current Job | B18: business, role, wage | C18: At most ONE personal shift across the agent's entire portfolio at a time
A19: Per-Role Skill Hours | B19: 8 counters (one per wage role) | C19: Cumulative hours worked at that role name, shared across every business of that type — see Wages tab Skill Progression
A20: Reputation / Bounty Status | B20: clean/wanted, total stacked amount, contributing crimes list | C20: Only confirmed via police witness — see Government & Insurance tab
A21: Guild Membership | B21: Guild ID + is-leader flag
A22: Health | B22: 0-100
A23: Alive / Dead + Respawn Timer | B23: boolean + countdown | C23: 60 sec respawn delay — see Combat & Heroes tab
A24: Insurance Policies Held | B24: Life / Asset, coverage amounts | C24: See Government & Insurance tab
A25: Memory Log | B25: significance-tagged event history | C25: Feeds the daily/rollup report generator
A27: 2. BUSINESS
A28: Field | B28: Type / Format | C28: Notes
A29: Business ID | B29: unique ID
A30: Name / Type | B30: enum | C30: One of 11 types — see Businesses tab
A31: Owner | B31: Agent ID or 'Government' | C31: Government-owned = always fully staffed regardless of actual employee count (see note below)
A32: Cash Balance | B32: number | C32: Drives the 24-hr bankruptcy grace period. N/A for Government-owned
A33: Employee Roster | B33: list: agent, role, wage
A34: Current Inventory Held | B34: list
A35: Retail Prices Set | B35: per-good price | C35: Player-owned only — NPC businesses use the fixed Assumptions-tab formula
A36: Research State | B36: RP accumulated, tier per track, Quality pool allocation | C36: See Research tab
A37: Active Production State | B37: what's being produced, by whom
A38: Insurance Brokerage Only: Cash Reserve | B38: number | C38: Must stay ≥ 70% of total outstanding insured value to issue new policies
A40: 3. VEHICLE
A41: Field | B41: Type / Format | C41: Notes
A42: Vehicle ID | B42: unique ID
A43: Type | B43: enum | C43: One of 6 — see Vehicles tab
A44: Owner | B44: Agent ID
A45: Current Location | B45: named location or transit state
A46: Current Cargo Load | B46: 0 to max capacity | C46: Capacity by type — see Vehicles tab
A47: Condition | B47: functional / damaged / destroyed
A48: Currently Mounted By | B48: Agent ID or none
A50: 4. PROPERTY
A51: Field | B51: Type / Format | C51: Notes
A52: Property ID | B52: unique ID
A53: Owner | B53: Agent ID
A54: Location | B54: named location
A55: Garage Tier | B55: 0-3 | C55: Vehicle slot count — see pricing table below
A56: Storage Tier | B56: 0-3 | C56: Unit capacity — see pricing table below
A57: Structures / Upgrades Built | B57: list
A58: Rental Status | B58: rented to whom, if any
A60: 5. CONVOY (only exists while active)
A61: Field | B61: Type / Format | C61: Notes
A62: Convoy ID | B62: unique ID
A63: Organizer | B63: Business ID + Agent ID
A64: Status | B64: enum | C64: Recruiting (elapsed time, extension count) / Loading / In-Transit (%) / Arrived / Ambushed / Destroyed / Cancelled
A65: Roster | B65: list: agent, role, vehicle | C65: Driver required per vehicle; Scout/Bodyguard optional
A66: Cargo Manifest | B66: good, quantity, value, owner attribution | C66: Aggregated before departure — convoys never visit individual farms/mines directly
A67: Pay Terms | B67: flat fee + commission per role | C67: Government baseline or custom if a player owns the organizing business — see Convoy tab
A68: Vehicles Used | B68: count | C68: Max 10
A69: Event Log | B69: this run only | C69: Feeds the daily report
A71: 6. MARKET
A72: Field | B72: Type / Format | C72: Notes
A73: Listed Price | B73: per good, per business | C73: Player-owned only — NPC follows the fixed Assumptions formula
A74: Transaction Log | B74: list | C74: Feeds price-trend reporting
A76: 7. GUILD
A77: Field | B77: Type / Format | C77: Notes
A78: Guild ID | B78: unique ID
A79: Name | B79: string
A80: Leader | B80: Agent ID | C80: Can remove any member
A81: Member List | B81: list of Agent IDs | C81: Uncapped size
A82: Chat Log | B82: list | C82: Private to members
A84: 8. BOUNTY
A85: Field | B85: Type / Format | C85: Notes
A86: Target Agent ID | B86: Agent ID
A87: Total Stacked Amount | B87: number | C87: Sum of every confirmed crime bounty against this agent, plus player contributions
A88: Contributing Crimes | B88: list: type, base amount, timestamp, police-confirmed flag | C88: Theft 25% of value / Murder 300 (stacks per instance) / Sabotage 150 — see Government & Insurance tab
A89: Player-Added Contributions | B89: list: contributor, amount | C89: Uncapped
A90: Status | B90: active / paid
A92: 9. GOVERNMENT
A93: Field | B93: Type / Format | C93: Notes
A94: Current Tax Rates | B94: Wage % / Sales % / Property % | C94: Start at 5% each, bounded 0-25% — see Assumptions tab and Government & Insurance tab
A95: Active Policies Enacted | B95: list, typed | C95: Bundled infrastructure/police (moves all 3 taxes together) / standalone tax nudge / bounty multiplier
A96: Police Tier | B96: 0-3 | C96: Current dispatch capacity and response time — see Government & Insurance tab
A97: Treasury Balance | B97: number | C97: Tracked for reporting only — enacted policies are funded by the ongoing tax RATE, not by drawing this down
A98: Active Proposals | B98: proposer, co-signers, vote tally, status | C98: Needs co-signers to reach ballot, 2/3 to enact
A99: Policy History | B99: enacted/reversed log | C99: 2/3 to reverse — restores both service level and tax delta together
A101: 10. WORLD
A102: Field | B102: Type / Format | C102: Notes
A103: Simulation Clock | B103: hour 0-120 | C103: Real time, no compression
A104: Government-Owned Businesses | B104: fixed list, one per type | C104: Exist from hour zero, always fully staffed regardless of real hires — agents are expected to recognize they can undercut them
A105: Global Event Log | B105: raw feed | C105: Source for daily + rollup reports
A106: Named Location Graph | B106: Refinery Row, North Protected Zone, The Hills, The Crossing, The Climb, South Protected Zone, Town | C106: ~5 min full transit at Medium speed. Offshoot spur roads (30-60 sec, dead-end loops back to the same point) connect individual mines/farms/homes — convoys never use these, only individual solo trips do
A108: GARAGE & STORAGE UPGRADE PRICING (referenced by Property entity)
A109: Item | B109: Cost | C109: Capacity | D109: Inputs
A110: Property Plot (base) | B110: 500 | C110: 20-unit storage, 0 garage slots included | D110: —
A111: Garage Tier 1 | B111: 200 | C111: 1 vehicle slot | D111: Stone + Wood
...

Sheet Combat & Heroes
A1: Combat Resolution & Hero Model Roster
A2: No hardcoded hit-chance percentage. Combat resolves in ~6-SECOND ROUNDS — both agents commit to one choice that holds for the whole round, and the weapon's real Attack Speed stat determines how many swings land inside that round. COMBAT DECISIONS SPECIFICALLY ROUTE THROUGH EACH AGENT'S FAST/NON-REASONING FALLBACK (GPT-5.6 Luna or Grok 4.3, both non-reasoning, ~3.5-5s response), regardless of which model that agent normally uses for economic decisions — every other decision type stays on the agent's full assigned model, since only combat has a tight latency requirement. TREAT 6 SECONDS AS A PROPOSAL, NOT FINAL — verify real round-trip latency for the fallback models during Phase 2 before locking it in.
A4: COMBAT RESOLUTION — ZONE-BASED, SIMULTANEOUS CHOICE
A5: • | B5: Each exchange occurs on the ATTACKER's weapon Attack Speed interval (see Weapons tab).
A6: • | B6: ATTACKER chooses a Target Zone: High / Center / Low — no visibility into the Defender's choice that exchange.
A7: • | B7: DEFENDER simultaneously chooses a Reaction: Block-High / Block-Center / Block-Low / Dodge / Counter-Attack.
A9: Defender's Choice | B9: vs. Attacker's Target Zone | C9: Result
A10: Block (matching zone) | B10: Same zone as attack | C10: Fully blocked — 0 damage
A11: Block (wrong zone) | B11: Different zone than guarded | C11: Full damage lands
A12: Dodge | B12: Any zone | C12: Fully evaded — 0 damage, but Defender forfeits their own attack this exchange
A13: Counter-Attack | B13: Any zone | C13: No defensive bonus — both agents' attacks land simultaneously (a genuine trade)
A15: Damage, Attack Speed, and Headshot/Backstab multipliers per weapon are on the Weapons tab and apply whenever a hit lands under this resolution. Armor's damage reduction (Armor tab) applies multiplicatively on top of whatever raw damage lands.
A17: RESPAWN
A18: • | B18: 60 second respawn delay on death.
A19: • | B19: Spawns at the agent's own Property, if they own one.
A20: • | B20: If no owned Property: spawns at Town (Town Square, near the Stores).
A21: • | B21: Carried inventory/Denari is lost at the death location (lootable by others) unless Life Insurance is held — see Government & Insurance tab for the 70% payout.
A22: • | B22: Owned vehicle/property/business ownership is unaffected by death UNLESS uninsured and left unclaimed for 24 hours (Asset Insurance rule).
A24: AGENT POPULATION & MODEL ROSTER
A25: 75 agents total, 15 per model, running 120 real hours nonstop (no time compression) for the validation sandbox — a smaller, cheaper population than the eventual full content-generation run, but large enough that all 11 business types have a real chance at genuine player-owned competition, not just the lone NPC version. All 5 models accessed through OpenRouter (one account, one API key). Note: 'low/medium/xhigh/max' labels are REASONING-EFFORT PARAMETERS on the underlying model, not separate model IDs — set via the API request, not the model string. One slot (Grok 4.3) is a deliberately weak, fast, cheap baseline included on purpose — see Role column.
A26: Model | B26: Agents | C26: Rate (per MTok) | D26: OpenRouter ID (verify at build time) | E26: Role in Test
A27: GPT-5.6 Terra (high) | B27: 15 | C27: $5 / $30 (high effort) | D27: openai/gpt-5.6-terra | E27: High-intelligence anchor — Intelligence 50, ~half the cost and half the response time of Opus 5 (low) for nearly identical intelligence. Strict upgrade.
A28: Ling 3.0 Flash | B28: 15 | C28: $0.04/task (exact input/output MTok split not available — verify on OpenRouter listing) | D28: inclusionai/ling-3.0-flash | E28: Second deliberately weaker/cheap/fast baseline — Intelligence 38, complements Grok 4.3 (Intelligence 25) as a second lower-capability comparison point, since GPT-5.6 Terra and DeepSeek V4 Flash already cover intelligence in this roster. 404 tokens/s median, 8.19s total response.
A29: DeepSeek V4 Flash 0731 (max) | B29: 15 | C29: ~$0.03/task equiv. | D29: deepseek/deepseek-v4-flash | E29: Intelligence 52 at a fraction of Opus's cost — best value in the roster
A30: Grok 4.3 (Non-reasoning) | B30: 15 | C30: $1.25 / $2.50 | D30: x-ai/grok-4.3 | E30: DELIBERATE WEAK BASELINE — Intelligence 25, fast and cheap, included specifically to see how a clearly weaker model performs against the other four
A31: GPT-5.6 Luna (medium) | B31: 15 | C31: $0.20 / $1.20 | D31: openai/gpt-5.6-luna | E31: Best overall value in the full comparison table — cheap, fast, solid mid-tier intelligence (39)
A33: Cost estimate: see Agent Scheduling & Diary tab — decision frequency is now event-driven with a universal 15-minute re-evaluation checkpoint, so cost is usage-dependent rather than a single precise number. The old $144/$94 figures (75 agents, 120 hours) should be treated as a rough reference point, close to but not precisely the real figure. Exact OpenRouter model-ID strings should be verified against the live catalog before building — naming and pricing can shift as providers update.
A34: Background population note: at this 75-agent validation scale, every agent runs a real model — there is no separate cheap rule-based tier the way the original 100-agent content-generation design used. The 5-hero, camera-focused, high-effort flagship roster (for streaming/marketing) is a SEPARATE later run, not this one.
A36: COMBAT ROUND MECHANICS — SWINGS PER ROUND
A37: Swings landed in one round = ROUND LENGTH ÷ Weapon Attack Speed (rounded down). Both fighters hold their Target Zone / Reaction choice for every swing in the round — one correct-or-wrong read is repeated, not re-decided per swing. A faster weapon means MORE swings riding on that single read, not more decisions.
A38: Weapon | B38: Attack Speed | C38: Swings per 3-sec Round
A39: Bronze Dagger / Iron Dagger | B39: 0.4s | C39: 7
A40: Bronze Sword / Iron Sword | B40: 0.6s | C40: 5
A41: Wooden Spear | B41: 0.7s | C41: 4
A42: Bronze-Tipped / Iron-Tipped Spear | B42: 0.75s | C42: 4
A43: Sling | B43: 0.8s | C43: 3
A44: Bow | B44: 0.85s | C44: 3
A45: Slingshot | B45: 0.9s | C45: 3
A47: CONVOY AMBUSH — DRIVER'S THREE-WAY CHOICE
A48: When a convoy is ambushed, Guards/Bodyguards enter the round-based combat loop above directly — that's their job. Each vehicle's DRIVER instead gets a real three-way choice, decided independently per vehicle (a 10-vehicle convoy can fragment under attack, with different Drivers choosing differently):
A49: Choice | B49: Effect
A50: Fight | B50: Driver joins combat directly using the round mechanic above, same as a Guard — vehicle stops moving.
A51: Push Through | B51: Vehicle keeps moving toward its destination at normal speed. Driver takes FULL, UNMITIGATED combat damage each round — no defensive reduction of any kind. Prioritizes cargo delivery over survival, full stop.
A52: Flee Off-Road | B52: Vehicle leaves the road at 50% speed (existing off-road rule). Unpredictable but slower, likely reduces Scout tracking effectiveness since Scouts watch the road, not open terrain.

Sheet Agent Scheduling & Diary
A1: Agent Decision Scheduling & Hourly Diary
A2: Every agent's underlying objective is always maximizing Net Worth. Decisions trigger two ways: IMMEDIATELY on task completion or an interrupt, and on a UNIVERSAL 15-simulated-minute re-evaluation checkpoint that applies to every agent regardless of current activity — not just idle ones. This replaces the earlier 'idle-only heartbeat' concept, which missed a real scenario: an agent 20 minutes into a 2-hour mining commitment needs a real chance to notice a much better convoy job posting, not just wait for mining to finish on its own. The underlying world clock still runs continuously in true real time (no compression); this only governs how often an AGENT gets a fresh decision point, not any time-based game rule.
A4: WHAT TRIGGERS A NEW DECISION
A5: • | B5: Current activity concludes — a mining/farming/refining session ends, travel arrives at its destination, a craft finishes. A 4-hour mining session is ONE decision followed by silence until it resolves, not repeated check-ins.
A6: • | B6: An interrupt occurs — the agent is attacked, robbed, witnesses a crime, is invited to a convoy, or a vote opens that affects them.
A7: • | B7: A short errand naturally chains — travel to town, buy an item, equip it can all happen back-to-back within a minute, each a real fast decision, with no artificial gap enforced between them.
A8: • | B8: Universal 15-minute re-evaluation checkpoint — EVERY agent, regardless of current task, gets a 'is what I'm doing still my best move, given anything new?' check every 15 simulated minutes. This can run as a lightweight, cheap check through the agent's fast fallback model (continue current task: yes/no) rather than a full expensive reasoning call every time — it only escalates to a full re-plan when the answer is genuinely 'no, something better exists now.'
A10: HOURLY DIARY
A11: Every agent writes a SHORT reflection every simulated hour, regardless of what else happened — even a 'mining, nothing notable, 3 hours left' entry during a long passive stretch. This is a SEPARATE, fixed-cadence call — it does not replace or compete with a real game decision, and it is the backbone the daily/rollup report generator draws from, so reports don't have to reconstruct a narrative from a ragged, variable-density action log. Feeds the Agent entity's Memory Log field (World State Schema tab).
A13: COST IMPACT — NO LONGER A FIXED FORMULA
A14: The universal 15-minute re-evaluation checkpoint brings real cost estimates back CLOSE TO the original $144 uncached / $94 cached ceiling (75 agents, 120 hours) — NOT clearly below it, correcting an earlier claim in this design process that event-driven scheduling would obviously undercut that number. What keeps cost reasonable is that most 15-minute checkpoints can be a lightweight, cheap continue-or-replan check via the fast fallback model rather than a full reasoning call every time, only escalating to the agent's full assigned model when something genuinely changed. Treat the real figure as something the validation run itself will reveal.

Sheet Sustenance
A1: Sustenance — Eating, Status Effects & Death
A2: Every agent must eat periodically or suffer escalating penalties, then death. Two paths: SELF-PREP (free, DIY, Grain + Water consumed directly from own inventory, always resets to the 12-hour base window) or a TAVERN MEAL (costs money, can be a higher Research tier for a longer window). Rest is NOT a separate mechanic — Sustenance is the only survival system.
A4: SUSTENANCE WINDOW — HOW LONG ONE MEAL LASTS BEFORE PENALTIES BEGIN
A5: Meal Type | B5: Duration | C5: Price
A6: Self-Prep (Grain + Water, own inventory) | B6: 12 hrs | C6: Free
A7: Base Tavern Meal (no Research) | B7: 12 hrs | C7: $10
A8: Tier 1 Bread | B8: 15 hrs | C8: $15
A9: Tier 2 Bread | B9: 18 hrs | C9: $22
A10: Tier 3 — Fine Bread | B10: 21 hrs | C10: $30
A11: Tier 4 — Masterwork Bread | B11: 24 hrs | C11: $40
A12: Tier 5 — Legendary Bread | B12: 30 hrs | C12: $55
A14: STATUS ESCALATION — FIXED 12-HOUR STAGES ONCE THE WINDOW RUNS OUT
A15: The window (12-30 hrs depending on meal tier eaten) determines how long an agent stays at Normal status. Once it expires, the escalation stages themselves are FIXED at 12 hours each regardless of meal tier — a higher tier buys a longer safe window, not slower decay once hungry. Eating any meal, of any tier, resets the timer to 0 and re-applies that meal's window.
A16: Stage | B16: Duration | C16: Effect
A17: Normal | B17: 0 to [meal's window] | C17: No penalty
A18: Hungry | B18: Next 12 hrs after window expires | C18: -10% production/combat speed
A19: Starving | B19: Next 12 hrs after that | C19: -25% speed, -5 HP once on entering this stage
A20: Death | B20: After Hungry + Starving fully elapse | C20: Standard respawn — 60 sec delay, spawn at owned Property or Town, inventory lost unless Life Insurance held
A22: WORKED EXAMPLE
A23: An agent eats Tier 4 Masterwork Bread at hour 10. They stay Normal until hour 34 (10 + 24-hr window). If they don't eat again, Hungry runs hours 34-46, Starving runs hours 46-58, and they die of starvation at hour 58 if still unfed. Eating ANY meal at any point during this resets the clock to a fresh window.
